vhdl/axis-dsp-concept/skidbuffer.vhd
----------------------------------------------------------------------------------
-- Company:        
-- Engineer:       simon.burkhardt
-- 
-- Create Date:    2023-04-21
-- Design Name:    AXIS skidbuffer
-- Module Name:    tb_skid - bh
-- Project Name:   
-- Target Devices: 
-- Tool Versions:  GHDL 0.37
-- Description:    skidbuffer for pipelining a bus handshake
-- 
-- Dependencies:   
-- 
-- Revision:
-- Revision 0.01 - File Created
-- Additional Comments:
-- 
----------------------------------------------------------------------------------
library ieee;
use ieee.std_logic_1164.all;
use ieee.numeric_std.all;

entity skidbuffer is
  generic (
    DATA_WIDTH  : integer := 32;
    OPT_DATA_REG : boolean := True
  );
  port (
    clock     : in std_logic;
    reset_n   : in std_logic;

    s_valid_i : in  std_logic;
    s_last_i  : in  std_logic;
    s_ready_o : out std_logic;
    s_data_i  : in  std_logic_vector(DATA_WIDTH - 1 downto 0);

    m_valid_o : out std_logic;
    m_last_o  : out std_logic;
    m_ready_i : in  std_logic;
    m_data_o  : out std_logic_vector(DATA_WIDTH - 1 downto 0)
  );
end skidbuffer;

architecture arch_imp of skidbuffer is
  -- register signals
  signal reg_data  : std_logic_vector(DATA_WIDTH-1 downto 0) := (others => '0');
  signal reg_last  : std_logic := '0';
  signal reg_valid : std_logic := '0';
  signal reg_ready : std_logic := '0';

  -- skid buffer signals (only used when OPT_DATA_REG = '1')
  signal skd_data  : std_logic_vector(DATA_WIDTH-1 downto 0) := (others => '0');
  signal skd_last  : std_logic := '0';

  -- output signals for output multiplexer
  signal out_data  : std_logic_vector(DATA_WIDTH-1 downto 0) := (others => '0');
  signal out_last  : std_logic := '0';

begin
  -- I/O connections assignments
  m_valid_o <= reg_valid;
  s_ready_o <= reg_ready;
  m_data_o  <= out_data;
  m_last_o  <= out_last;

  -- ready is always registered
  p_reg_ready : process(clock)
  begin
    if rising_edge(clock) then 
      if reset_n = '0' then
        reg_ready <= '0';
      else
        reg_ready <= m_ready_i;
      end if;
    end if;
  end process;

-- NOT REGISTERED OUTPUT -------------------------------------------------------
  gen_no_register : if not OPT_DATA_REG generate
    reg_valid <= s_valid_i; -- valid is not registered
    -- output multiplexer
    out_data <= reg_data when (reg_ready = '0') else s_data_i;
    out_last <= reg_last when (reg_ready = '0') else s_last_i;

    p_reg : process (clock)
    begin
      if rising_edge(clock) then 
        if reset_n = '0' then
          reg_data  <= (others => '0');
          reg_last  <= '0';
        else
          if reg_ready = '1' then
            reg_data <= s_data_i;
            reg_last <= s_last_i;
          else
            reg_data <= reg_data;
            reg_last <= reg_last;
          end if;
        end if;
      end if;
    end process;
    
  end generate;

-- FULLY REGISTERED OUTPUT -----------------------------------------------------
  gen_data_register : if OPT_DATA_REG generate
    out_data <= reg_data;
    out_last <= reg_last;
    -- registered output signals
    p_reg : process (clock)
    begin
      if rising_edge(clock) then 
        if reset_n = '0' then
          reg_data  <= (others => '0');
          reg_last  <= '0';
          skd_data  <= (others => '0');
          skd_last  <= '0';
          reg_valid <= '0';
        else
          reg_valid <= s_valid_i;
          if reg_ready = '1' then
            skd_data <= s_data_i;
            skd_last <= s_last_i;
          else
            skd_data <= skd_data;
            skd_last <= skd_last;
          end if;

          if m_ready_i = '0' then
            reg_data <= reg_data;
            reg_last <= reg_last;
          else
            if reg_ready = '1' then
              reg_data <= s_data_i;
              reg_last <= s_last_i;
            else
              reg_data <= skd_data;
              reg_last <= skd_last;
            end if;
          end if;
        end if;
      end if;
    end process;
  end generate;

end arch_imp;

ghdl/axis-dsp-concept/axis_my_dsp.vhd
----------------------------------------------------------------------------------
-- Company:        
-- Engineer:       simon.burkhardt
-- 
-- Create Date:    
-- Design Name:    
-- Module Name:    
-- Project Name:   
-- Target Devices: 
-- Tool Versions:  
-- Description:    
-- 
-- Dependencies:   
-- 
-- Revision:
-- Revision 0.01 - File Created
-- Additional Comments:
-- 
----------------------------------------------------------------------------------
library ieee;
use ieee.std_logic_1164.all;
use ieee.numeric_std.all;

entity axis_my_dsp is
  generic (
    C_S_AXIS_TDATA_WIDTH  : integer := 32
  );
  port (
    AXIS_ACLK : in std_logic;

    S_AXIS_TVALID : in  std_logic;
    S_AXIS_TDATA  : in  std_logic_vector(C_S_AXIS_TDATA_WIDTH-1 downto 0);
    S_AXIS_TREADY : out std_logic;

    M_AXIS_TVALID : out std_logic;
    M_AXIS_TDATA  : out std_logic_vector(C_S_AXIS_TDATA_WIDTH-1 downto 0);
    M_AXIS_TREADY : in  std_logic
  );
end axis_my_dsp;

architecture arch_imp of axis_my_dsp is
  component skidbuffer is
    generic (
      DATA_WIDTH   : integer;
      OPT_DATA_REG : boolean
    );
    port (
      clock     : in std_logic;
      reset_n   : in std_logic;

      s_valid_i : in  std_logic;
      s_last_i  : in  std_logic;
      s_ready_o : out std_logic;
      s_data_i  : in  std_logic_vector(DATA_WIDTH - 1 downto 0);

      m_valid_o : out std_logic;
      m_last_o  : out std_logic;
      m_ready_i : in  std_logic;
      m_data_o  : out std_logic_vector(DATA_WIDTH - 1 downto 0)
    );
  end component;

  -- signals
  signal s_tvalid_skd : std_logic := '0';
  signal s_tdata_skd  : std_logic_vector(C_S_AXIS_TDATA_WIDTH-1 downto 0) := (others => '0');
  signal s_tready_skd : std_logic := '0';

  signal m_tvalid_skd : std_logic := '0';
  signal m_tdata_skd  : std_logic_vector(C_S_AXIS_TDATA_WIDTH-1 downto 0) := (others => '0');
  signal m_tready_skd : std_logic := '0';

  type tap_t is array (0 to 3) of signed(C_S_AXIS_TDATA_WIDTH-1 downto 0);
  signal taps : tap_t := (OTHERS => (OTHERS => '0'));
  type valid_t is array (0 to 3) of std_logic;
  signal valid_chain : valid_t := (OTHERS => '0');

begin

  upstream_buffer : skidbuffer
    generic map (
      DATA_WIDTH   => C_S_AXIS_TDATA_WIDTH,
      OPT_DATA_REG => True
    )
    port map (
      clock     => AXIS_ACLK,
      reset_n   => '1',
      s_valid_i => S_AXIS_TVALID,
      s_last_i  => '0',
      s_ready_o => S_AXIS_TREADY,
      s_data_i  => S_AXIS_TDATA,
      m_valid_o => s_tvalid_skd,
      m_last_o  => open,
      m_ready_i => s_tready_skd,
      m_data_o  => s_tdata_skd
    );

  s_tready_skd <= m_tready_skd;

  p_dsp_algorithm : process(AXIS_ACLK)
  begin 
    if rising_edge(AXIS_ACLK) then
      valid_chain(0) <= s_tvalid_skd;
      for i in 0 to 2 loop
        valid_chain(i+1) <= valid_chain(i);
      end loop;

      if s_tvalid_skd='1' and m_tready_skd='1' then
        taps(0) <= signed(s_tdata_skd)+1;
      end if;

      if valid_chain(0)='1' and m_tready_skd='1' then
        taps(1) <= taps(0) +1;
      end if;
      if valid_chain(1)='1' and m_tready_skd='1' then
        taps(2) <= taps(1) +1;
      end if;
      if valid_chain(2)='1' and m_tready_skd='1' then
        taps(3) <= taps(2) +1;
      end if;
    end if;
  end process;

  m_tdata_skd <= std_logic_vector(taps(3));
  m_tvalid_skd <= valid_chain(3);

  downstream_buffer : skidbuffer
    generic map (
      DATA_WIDTH   => C_S_AXIS_TDATA_WIDTH,
      OPT_DATA_REG => True
    )
    port map (
      clock     => AXIS_ACLK,
      reset_n   => '1',
      s_valid_i => m_tvalid_skd,
      s_last_i  => '0',
      s_ready_o => m_tready_skd,
      s_data_i  => m_tdata_skd,
      m_valid_o => M_AXIS_TVALID,
      m_last_o  => open,
      m_ready_i => M_AXIS_TREADY,
      m_data_o  => M_AXIS_TDATA
    );

end arch_imp;

vhdl/axis-dsp-concept/tb_axis_my_dsp.vhd
----------------------------------------------------------------------------------
-- Company:        
-- Engineer:       simon.burkhardt
-- 
-- Create Date:    
-- Design Name:    
-- Module Name:    
-- Project Name:   
-- Target Devices: 
-- Tool Versions:  
-- Description:    
-- 
-- Dependencies:   
-- 
-- Revision:
-- Revision 0.01 - File Created
-- Additional Comments:
-- 
----------------------------------------------------------------------------------

library ieee;
use ieee.std_logic_1164.all;
use ieee.numeric_std.all;


entity tb_axis_my_dsp is
  generic
  (
    DATA_WIDTH   : natural := 8;
    OPT_DATA_REG : boolean := True
  );
end tb_axis_my_dsp;

architecture bh of tb_axis_my_dsp is
  -- DUT component declaration
  component axis_my_dsp is
    generic (
      C_S_AXIS_TDATA_WIDTH  : integer := 32
    );
    port (
      AXIS_ACLK : in std_logic;
 
      S_AXIS_TVALID : in  std_logic;
      S_AXIS_TDATA  : in  std_logic_vector(C_S_AXIS_TDATA_WIDTH-1 downto 0);
      S_AXIS_TREADY : out std_logic;
 
      M_AXIS_TVALID : out std_logic;
      M_AXIS_TDATA  : out std_logic_vector(C_S_AXIS_TDATA_WIDTH-1 downto 0);
      M_AXIS_TREADY : in  std_logic
    );
  end component;
  
  constant CLK_PERIOD: TIME := 5 ns;

  signal sim_valid_data  : std_logic := '0';
  signal sim_ready_data  : std_logic := '1';

  signal s_axis_tvalid : std_logic := '0';
  signal s_axis_tdata  : std_logic_vector(DATA_WIDTH-1 downto 0) := (others => '0');
  signal s_axis_tready : std_logic := '0';

  signal m_axis_tvalid : std_logic := '0';
  signal m_axis_tdata  : std_logic_vector(DATA_WIDTH-1 downto 0) := (others => '0');
  signal m_axis_tready : std_logic := '0';

  signal clk   : std_logic;
  signal rst_n : std_logic;

  signal clk_count : unsigned(7 downto 0) := (others => '0');
  signal sim_value  : unsigned(7 downto 0) := (others => '0');
begin

  -- generate clk signal
  p_clk_gen : process
  begin
   clk <= '1';
   wait for (CLK_PERIOD / 2);
   clk <= '0';
   wait for (CLK_PERIOD / 2);
   clk_count <= clk_count + 1;
  end process;

  -- generate initial reset
  p_reset_gen : process
  begin 
    rst_n <= '0';
    wait until rising_edge(clk);
    wait for (CLK_PERIOD / 4);
    rst_n <= '1';
    wait;
  end process;

  -- generate ready signal
  p_stimuli_tready : process(clk)
  begin
    if rising_edge(clk) then
      if clk_count = 3 then
        m_axis_tready <= '1';
      end if;

      if clk_count = 24 then
        m_axis_tready <= '0';
      end if;
      if clk_count = 25 then
        m_axis_tready <= '1';
      end if;
      if clk_count = 30 then
        m_axis_tready <= '0';
      end if;
      if clk_count = 32 then
        m_axis_tready <= '1';
      end if;
    end if;
  end process;

  -- generate valid signal
  p_stimuli_tvalid : process(clk)
  begin
    if rising_edge(clk) then
      if clk_count = 5 then
        sim_valid_data <= '1';
      end if;
      if clk_count = 6 then
        sim_valid_data <= '0';
      end if;

      if clk_count = 10 then
        sim_valid_data <= '1';
      end if;
      if clk_count = 12 then
        sim_valid_data <= '0';
      end if;

      if clk_count = 20 then
        sim_valid_data <= '1';
      end if;
    end if;
  end process;

  -- generate counter data when successfully acknowledged (tready) by slave
  p_stimuli_tdata : process(clk)
  begin
    if rising_edge(clk) then
      if sim_valid_data = '1' then
        s_axis_tvalid <= '1';
        if s_axis_tready = '1' then
          s_axis_tdata <= std_logic_vector(sim_value);
          sim_value <= sim_value+1;
        end if;
      else
        s_axis_tvalid <= '0';
      end if;
    end if;
  end process;

-- DUT instance and connections
  skidbuffer_inst : axis_my_dsp
  generic map (
    C_S_AXIS_TDATA_WIDTH  => DATA_WIDTH
  )
  port map (
    AXIS_ACLK     => clk,

    S_AXIS_TVALID => s_axis_tvalid,
    S_AXIS_TDATA  => s_axis_tdata, 
    S_AXIS_TREADY => s_axis_tready, 

    M_AXIS_TVALID => m_axis_tvalid, 
    M_AXIS_TDATA  => m_axis_tdata, 
    M_AXIS_TREADY => m_axis_tready
  );

end bh;

ghdl/axis-dsp-concept/wave.vcd
$date
  Wed Dec 13 12:01:43 2023
$end
$version
  GHDL v0
$end
$timescale
  1 fs
$end
$scope module standard $end
$upscope $end
$scope module std_logic_1164 $end
$upscope $end
$scope module numeric_std $end
$upscope $end
$scope module tb_axis_my_dsp $end
$var reg 1 ! sim_valid_data $end
$var reg 1 " sim_ready_data $end
$var reg 1 # s_axis_tvalid $end
$var reg 8 $ s_axis_tdata[7:0] $end
$var reg 1 % s_axis_tready $end
$var reg 1 & m_axis_tvalid $end
$var reg 8 ' m_axis_tdata[7:0] $end
$var reg 1 ( m_axis_tready $end
$var reg 1 ) clk $end
$var reg 1 * rst_n $end
$var reg 8 + clk_count[7:0] $end
$var reg 8 , sim_value[7:0] $end
$scope module skidbuffer_inst $end
$var reg 1 - axis_aclk $end
$var reg 1 . s_axis_tvalid $end
$var reg 8 / s_axis_tdata[7:0] $end
$var reg 1 0 s_axis_tready $end
$var reg 1 1 m_axis_tvalid $end
$var reg 8 2 m_axis_tdata[7:0] $end
$var reg 1 3 m_axis_tready $end
$var reg 1 4 s_tvalid_skd $end
$var reg 8 5 s_tdata_skd[7:0] $end
$var reg 1 6 s_tready_skd $end
$var reg 1 7 m_tvalid_skd $end
$var reg 8 8 m_tdata_skd[7:0] $end
$var reg 1 9 m_tready_skd $end
$comment taps is not handled $end
$var reg 4 : valid_chain[0:3] $end
$scope module upstream_buffer $end
$var reg 1 ; clock $end
$var reg 1 < reset_n $end
$var reg 1 = s_valid_i $end
$var reg 1 > s_last_i $end
$var reg 1 ? s_ready_o $end
$var reg 8 @ s_data_i[7:0] $end
$var reg 1 A m_valid_o $end
$var reg 1 B m_last_o $end
$var reg 1 C m_ready_i $end
$var reg 8 D m_data_o[7:0] $end
$var reg 8 E reg_data[7:0] $end
$var reg 1 F reg_last $end
$var reg 1 G reg_valid $end
$var reg 1 H reg_ready $end
$var reg 8 I skd_data[7:0] $end
$var reg 1 J skd_last $end
$var reg 8 K out_data[7:0] $end
$var reg 1 L out_last $end
$scope module gen_data_register $end
$upscope $end
$upscope $end
$scope module downstream_buffer $end
$var reg 1 M clock $end
$var reg 1 N reset_n $end
$var reg 1 O s_valid_i $end
$var reg 1 P s_last_i $end
$var reg 1 Q s_ready_o $end
$var reg 8 R s_data_i[7:0] $end
$var reg 1 S m_valid_o $end
$var reg 1 T m_last_o $end
$var reg 1 U m_ready_i $end
$var reg 8 V m_data_o[7:0] $end
$var reg 8 W reg_data[7:0] $end
$var reg 1 X reg_last $end
$var reg 1 Y reg_valid $end
$var reg 1 Z reg_ready $end
$var reg 8 [ skd_data[7:0] $end
$var reg 1 \ skd_last $end
$var reg 8 ] out_data[7:0] $end
$var reg 1 ^ out_last $end
$scope module gen_data_register $end
$upscope $end
$upscope $end
$upscope $end
$upscope $end
$enddefinitions $end
#0
0!
1"
0#
b00000000 $
0%
0&
b00000000 '
0(
1)
0*
b00000000 +
b00000000 ,
1-
0.
b00000000 /
00
01
b00000000 2
03
04
b00000000 5
06
07
b00000000 8
09
b0000 :
1;
1<
0=
0>
0?
b00000000 @
0A
0B
0C
b00000000 D
b00000000 E
0F
0G
0H
b00000000 I
0J
b00000000 K
0L
1M
1N
0O
0P
0Q
b00000000 R
0S
0T
0U
b00000000 V
b00000000 W
0X
0Y
0Z
b00000000 [
0\
b00000000 ]
0^
#2500000
0)
0-
0;
0M
#5000000
1)
b00000001 +
1-
1;
1M
#6250000
1*
#7500000
0)
0-
0;
0M
#10000000
1)
b00000010 +
1-
1;
1M
#12500000
0)
0-
0;
0M
#15000000
1(
1)
b00000011 +
1-
13
1;
1M
1U
#17500000
0)
0-
0;
0M
#20000000
1)
b00000100 +
1-
16
19
1;
1C
1M
1Q
1Z
#22500000
0)
0-
0;
0M
#25000000
1!
1%
1)
b00000101 +
1-
10
1;
1?
1H
1M
#27500000
0)
0-
0;
0M
#30000000
0!
1#
1)
b00000110 +
b00000001 ,
1-
1.
1;
1=
1M
#32500000
0)
0-
0;
0M
#35000000
0#
1)
b00000111 +
1-
0.
14
1;
0=
1A
1G
1M
#37500000
0)
0-
0;
0M
#40000000
1)
b00001000 +
1-
04
b1000 :
1;
0A
0G
1M
#42500000
0)
0-
0;
0M
#45000000
1)
b00001001 +
1-
b0100 :
1;
1M
#47500000
0)
0-
0;
0M
#50000000
1!
1)
b00001010 +
1-
b0010 :
1;
1M
#52500000
0)
0-
0;
0M
#55000000
1#
b00000001 $
1)
b00001011 +
b00000010 ,
1-
1.
b00000001 /
17
b00000100 8
b0001 :
1;
1=
b00000001 @
1M
1O
b00000100 R
#57500000
0)
0-
0;
0M
#60000000
0!
b00000010 $
1&
b00000100 '
1)
b00001100 +
b00000011 ,
1-
b00000010 /
11
b00000100 2
14
b00000001 5
07
b0000 :
1;
b00000010 @
1A
b00000001 D
b00000001 E
1G
b00000001 I
b00000001 K
1M
0O
1S
b00000100 V
b00000100 W
1Y
b00000100 [
b00000100 ]
#62500000
0)
0-
0;
0M
#65000000
0#
0&
1)
b00001101 +
1-
0.
01
b00000010 5
b1000 :
1;
0=
b00000010 D
b00000010 E
b00000010 I
b00000010 K
1M
0S
0Y
#67500000
0)
0-
0;
0M
#70000000
1)
b00001110 +
1-
04
b1100 :
1;
0A
0G
1M
#72500000
0)
0-
0;
0M
#75000000
1)
b00001111 +
1-
b0110 :
1;
1M
#77500000
0)
0-
0;
0M
#80000000
1)
b00010000 +
1-
17
b00000101 8
b0011 :
1;
1M
1O
b00000101 R
#82500000
0)
0-
0;
0M
#85000000
1&
b00000101 '
1)
b00010001 +
1-
11
b00000101 2
b00000110 8
b0001 :
1;
1M
b00000110 R
1S
b00000101 V
b00000101 W
1Y
b00000101 [
b00000101 ]
#87500000
0)
0-
0;
0M
#90000000
b00000110 '
1)
b00010010 +
1-
b00000110 2
07
b0000 :
1;
1M
0O
b00000110 V
b00000110 W
b00000110 [
b00000110 ]
#92500000
0)
0-
0;
0M
#95000000
0&
1)
b00010011 +
1-
01
1;
1M
0S
0Y
#97500000
0)
0-
0;
0M
#100000000
1!
1)
b00010100 +
1-
1;
1M
#102500000
0)
0-
0;
0M
#105000000
1#
b00000011 $
1)
b00010101 +
b00000100 ,
1-
1.
b00000011 /
1;
1=
b00000011 @
1M
#107500000
0)
0-
0;
0M
#110000000
b00000100 $
1)
b00010110 +
b00000101 ,
1-
b00000100 /
14
b00000011 5
1;
b00000100 @
1A
b00000011 D
b00000011 E
1G
b00000011 I
b00000011 K
1M
#112500000
0)
0-
0;
0M
#115000000
b00000101 $
1)
b00010111 +
b00000110 ,
1-
b00000101 /
b00000100 5
b1000 :
1;
b00000101 @
b00000100 D
b00000100 E
b00000100 I
b00000100 K
1M
#117500000
0)
0-
0;
0M
#120000000
b00000110 $
0(
1)
b00011000 +
b00000111 ,
1-
b00000110 /
03
b00000101 5
b1100 :
1;
b00000110 @
b00000101 D
b00000101 E
b00000101 I
b00000101 K
1M
0U
#122500000
0)
0-
0;
0M
#125000000
b00000111 $
1(
1)
b00011001 +
b00001000 ,
1-
b00000111 /
13
b00000110 5
06
09
b1110 :
1;
b00000111 @
0C
b00000110 D
b00000110 E
b00000110 I
b00000110 K
1M
0Q
1U
0Z
#127500000
0)
0-
0;
0M
#130000000
b00001000 $
0%
1)
b00011010 +
b00001001 ,
1-
b00001000 /
00
16
17
19
b1111 :
1;
0?
b00001000 @
1C
0H
b00000111 I
1M
1O
1Q
1Z
#132500000
0)
0-
0;
0M
#135000000
1%
1&
1)
b00011011 +
1-
10
11
b00000111 5
b00000111 8
1;
1?
b00000111 D
b00000111 E
1H
b00000111 K
1M
b00000111 R
1S
1Y
#137500000
0)
0-
0;
0M
#140000000
b00001001 $
b00000111 '
1)
b00011100 +
b00001010 ,
1-
b00001001 /
b00000111 2
b00001000 5
b00001000 8
1;
b00001001 @
b00001000 D
b00001000 E
b00001000 I
b00001000 K
1M
b00001000 R
b00000111 V
b00000111 W
b00000111 [
b00000111 ]
#142500000
0)
0-
0;
0M
#145000000
b00001010 $
b00001000 '
1)
b00011101 +
b00001011 ,
1-
b00001010 /
b00001000 2
b00001001 5
b00001001 8
1;
b00001010 @
b00001001 D
b00001001 E
b00001001 I
b00001001 K
1M
b00001001 R
b00001000 V
b00001000 W
b00001000 [
b00001000 ]
#147500000
0)
0-
0;
0M
#150000000
b00001011 $
b00001001 '
0(
1)
b00011110 +
b00001100 ,
1-
b00001011 /
b00001001 2
03
b00001010 5
b00001010 8
1;
b00001011 @
b00001010 D
b00001010 E
b00001010 I
b00001010 K
1M
b00001010 R
0U
b00001001 V
b00001001 W
b00001001 [
b00001001 ]
#152500000
0)
0-
0;
0M
#155000000
b00001100 $
1)
b00011111 +
b00001101 ,
1-
b00001100 /
b00001011 5
06
b00001011 8
09
1;
b00001100 @
0C
b00001011 D
b00001011 E
b00001011 I
b00001011 K
1M
0Q
b00001011 R
0Z
b00001010 [
#157500000
0)
0-
0;
0M
#160000000
b00001101 $
0%
1(
1)
b00100000 +
b00001110 ,
1-
b00001101 /
00
13
1;
0?
b00001101 @
0H
b00001100 I
1M
1U
#162500000
0)
0-
0;
0M
#165000000
b00001010 '
1)
b00100001 +
1-
b00001010 2
16
19
1;
1C
1M
1Q
b00001010 V
b00001010 W
1Z
b00001010 ]
#167500000
0)
0-
0;
0M
#170000000
1%
b00001011 '
1)
b00100010 +
1-
10
b00001011 2
b00001100 5
b00001100 8
1;
1?
b00001100 D
b00001100 E
1H
b00001100 K
1M
b00001100 R
b00001011 V
b00001011 W
b00001011 [
b00001011 ]
#172500000
0)
0-
0;
0M
#175000000
b00001110 $
b00001100 '
1)
b00100011 +
b00001111 ,
1-
b00001110 /
b00001100 2
b00001101 5
b00001101 8
1;
b00001110 @
b00001101 D
b00001101 E
b00001101 I
b00001101 K
1M
b00001101 R
b00001100 V
b00001100 W
b00001100 [
b00001100 ]
#177500000
0)
0-
0;
0M
#180000000
b00001111 $
b00001101 '
1)
b00100100 +
b00010000 ,
1-
b00001111 /
b00001101 2
b00001110 5
b00001110 8
1;
b00001111 @
b00001110 D
b00001110 E
b00001110 I
b00001110 K
1M
b00001110 R
b00001101 V
b00001101 W
b00001101 [
b00001101 ]
#182500000
0)
0-
0;
0M
#185000000
b00010000 $
b00001110 '
1)
b00100101 +
b00010001 ,
1-
b00010000 /
b00001110 2
b00001111 5
b00001111 8
1;
b00010000 @
b00001111 D
b00001111 E
b00001111 I
b00001111 K
1M
b00001111 R
b00001110 V
b00001110 W
b00001110 [
b00001110 ]
#187500000
0)
0-
0;
0M
#190000000
b00010001 $
b00001111 '
1)
b00100110 +
b00010010 ,
1-
b00010001 /
b00001111 2
b00010000 5
b00010000 8
1;
b00010001 @
b00010000 D
b00010000 E
b00010000 I
b00010000 K
1M
b00010000 R
b00001111 V
b00001111 W
b00001111 [
b00001111 ]
#192500000
0)
0-
0;
0M
#195000000
b00010010 $
b00010000 '
1)
b00100111 +
b00010011 ,
1-
b00010010 /
b00010000 2
b00010001 5
b00010001 8
1;
b00010010 @
b00010001 D
b00010001 E
b00010001 I
b00010001 K
1M
b00010001 R
b00010000 V
b00010000 W
b00010000 [
b00010000 ]
#197500000
0)
0-
0;
0M
#200000000
b00010011 $
b00010001 '
1)
b00101000 +
b00010100 ,
1-
b00010011 /
b00010001 2
b00010010 5
b00010010 8
1;
b00010011 @
b00010010 D
b00010010 E
b00010010 I
b00010010 K
1M
b00010010 R
b00010001 V
b00010001 W
b00010001 [
b00010001 ]
#202500000
0)
0-
0;
0M
#205000000
b00010100 $
b00010010 '
1)
b00101001 +
b00010101 ,
1-
b00010100 /
b00010010 2
b00010011 5
b00010011 8
1;
b00010100 @
b00010011 D
b00010011 E
b00010011 I
b00010011 K
1M
b00010011 R
b00010010 V
b00010010 W
b00010010 [
b00010010 ]
#207500000
0)
0-
0;
0M
#210000000
b00010101 $
b00010011 '
1)
b00101010 +
b00010110 ,
1-
b00010101 /
b00010011 2
b00010100 5
b00010100 8
1;
b00010101 @
b00010100 D
b00010100 E
b00010100 I
b00010100 K
1M
b00010100 R
b00010011 V
b00010011 W
b00010011 [
b00010011 ]
#212500000
0)
0-
0;
0M
#215000000
b00010110 $
b00010100 '
1)
b00101011 +
b00010111 ,
1-
b00010110 /
b00010100 2
b00010101 5
b00010101 8
1;
b00010110 @
b00010101 D
b00010101 E
b00010101 I
b00010101 K
1M
b00010101 R
b00010100 V
b00010100 W
b00010100 [
b00010100 ]
#217500000
0)
0-
0;
0M
#220000000
b00010111 $
b00010101 '
1)
b00101100 +
b00011000 ,
1-
b00010111 /
b00010101 2
b00010110 5
b00010110 8
1;
b00010111 @
b00010110 D
b00010110 E
b00010110 I
b00010110 K
1M
b00010110 R
b00010101 V
b00010101 W
b00010101 [
b00010101 ]
#222500000
0)
0-
0;
0M
#225000000
b00011000 $
b00010110 '
1)
b00101101 +
b00011001 ,
1-
b00011000 /
b00010110 2
b00010111 5
b00010111 8
1;
b00011000 @
b00010111 D
b00010111 E
b00010111 I
b00010111 K
1M
b00010111 R
b00010110 V
b00010110 W
b00010110 [
b00010110 ]
#227500000
0)
0-
0;
0M
#230000000
b00011001 $
b00010111 '
1)
b00101110 +
b00011010 ,
1-
b00011001 /
b00010111 2
b00011000 5
b00011000 8
1;
b00011001 @
b00011000 D
b00011000 E
b00011000 I
b00011000 K
1M
b00011000 R
b00010111 V
b00010111 W
b00010111 [
b00010111 ]
#232500000
0)
0-
0;
0M
#235000000
b00011010 $
b00011000 '
1)
b00101111 +
b00011011 ,
1-
b00011010 /
b00011000 2
b00011001 5
b00011001 8
1;
b00011010 @
b00011001 D
b00011001 E
b00011001 I
b00011001 K
1M
b00011001 R
b00011000 V
b00011000 W
b00011000 [
b00011000 ]
#237500000
0)
0-
0;
0M
#240000000
b00011011 $
b00011001 '
1)
b00110000 +
b00011100 ,
1-
b00011011 /
b00011001 2
b00011010 5
b00011010 8
1;
b00011011 @
b00011010 D
b00011010 E
b00011010 I
b00011010 K
1M
b00011010 R
b00011001 V
b00011001 W
b00011001 [
b00011001 ]
#242500000
0)
0-
0;
0M
#245000000
b00011100 $
b00011010 '
1)
b00110001 +
b00011101 ,
1-
b00011100 /
b00011010 2
b00011011 5
b00011011 8
1;
b00011100 @
b00011011 D
b00011011 E
b00011011 I
b00011011 K
1M
b00011011 R
b00011010 V
b00011010 W
b00011010 [
b00011010 ]
#247500000
0)
0-
0;
0M
#250000000
b00011101 $
b00011011 '
1)
b00110010 +
b00011110 ,
1-
b00011101 /
b00011011 2
b00011100 5
b00011100 8
1;
b00011101 @
b00011100 D
b00011100 E
b00011100 I
b00011100 K
1M
b00011100 R
b00011011 V
b00011011 W
b00011011 [
b00011011 ]
#252500000
0)
0-
0;
0M
#255000000
b00011110 $
b00011100 '
1)
b00110011 +
b00011111 ,
1-
b00011110 /
b00011100 2
b00011101 5
b00011101 8
1;
b00011110 @
b00011101 D
b00011101 E
b00011101 I
b00011101 K
1M
b00011101 R
b00011100 V
b00011100 W
b00011100 [
b00011100 ]
#257500000
0)
0-
0;
0M
#260000000
b00011111 $
b00011101 '
1)
b00110100 +
b00100000 ,
1-
b00011111 /
b00011101 2
b00011110 5
b00011110 8
1;
b00011111 @
b00011110 D
b00011110 E
b00011110 I
b00011110 K
1M
b00011110 R
b00011101 V
b00011101 W
b00011101 [
b00011101 ]
#262500000
0)
0-
0;
0M
#265000000
b00100000 $
b00011110 '
1)
b00110101 +
b00100001 ,
1-
b00100000 /
b00011110 2
b00011111 5
b00011111 8
1;
b00100000 @
b00011111 D
b00011111 E
b00011111 I
b00011111 K
1M
b00011111 R
b00011110 V
b00011110 W
b00011110 [
b00011110 ]
#267500000
0)
0-
0;
0M
#270000000
b00100001 $
b00011111 '
1)
b00110110 +
b00100010 ,
1-
b00100001 /
b00011111 2
b00100000 5
b00100000 8
1;
b00100001 @
b00100000 D
b00100000 E
b00100000 I
b00100000 K
1M
b00100000 R
b00011111 V
b00011111 W
b00011111 [
b00011111 ]
#272500000
0)
0-
0;
0M
#275000000
b00100010 $
b00100000 '
1)
b00110111 +
b00100011 ,
1-
b00100010 /
b00100000 2
b00100001 5
b00100001 8
1;
b00100010 @
b00100001 D
b00100001 E
b00100001 I
b00100001 K
1M
b00100001 R
b00100000 V
b00100000 W
b00100000 [
b00100000 ]
#277500000
0)
0-
0;
0M
#280000000
b00100011 $
b00100001 '
1)
b00111000 +
b00100100 ,
1-
b00100011 /
b00100001 2
b00100010 5
b00100010 8
1;
b00100011 @
b00100010 D
b00100010 E
b00100010 I
b00100010 K
1M
b00100010 R
b00100001 V
b00100001 W
b00100001 [
b00100001 ]
#282500000
0)
0-
0;
0M
#285000000
b00100100 $
b00100010 '
1)
b00111001 +
b00100101 ,
1-
b00100100 /
b00100010 2
b00100011 5
b00100011 8
1;
b00100100 @
b00100011 D
b00100011 E
b00100011 I
b00100011 K
1M
b00100011 R
b00100010 V
b00100010 W
b00100010 [
b00100010 ]
#287500000
0)
0-
0;
0M
#290000000
b00100101 $
b00100011 '
1)
b00111010 +
b00100110 ,
1-
b00100101 /
b00100011 2
b00100100 5
b00100100 8
1;
b00100101 @
b00100100 D
b00100100 E
b00100100 I
b00100100 K
1M
b00100100 R
b00100011 V
b00100011 W
b00100011 [
b00100011 ]
#292500000
0)
0-
0;
0M
#295000000
b00100110 $
b00100100 '
1)
b00111011 +
b00100111 ,
1-
b00100110 /
b00100100 2
b00100101 5
b00100101 8
1;
b00100110 @
b00100101 D
b00100101 E
b00100101 I
b00100101 K
1M
b00100101 R
b00100100 V
b00100100 W
b00100100 [
b00100100 ]
#297500000
0)
0-
0;
0M
#300000000
b00100111 $
b00100101 '
1)
b00111100 +
b00101000 ,
1-
b00100111 /
b00100101 2
b00100110 5
b00100110 8
1;
b00100111 @
b00100110 D
b00100110 E
b00100110 I
b00100110 K
1M
b00100110 R
b00100101 V
b00100101 W
b00100101 [
b00100101 ]
#302500000
0)
0-
0;
0M
#305000000
b00101000 $
b00100110 '
1)
b00111101 +
b00101001 ,
1-
b00101000 /
b00100110 2
b00100111 5
b00100111 8
1;
b00101000 @
b00100111 D
b00100111 E
b00100111 I
b00100111 K
1M
b00100111 R
b00100110 V
b00100110 W
b00100110 [
b00100110 ]
#307500000
0)
0-
0;
0M
