ghdl/basic/skidbuffer.vhd
----------------------------------------------------------------------------------
-- Company:        
-- Engineer:       simon.burkhardt
-- 
-- Create Date:    2023-04-21
-- Design Name:    Generic skidbuffer for AXI
-- Module Name:    skidbuffer
-- Project Name:   
-- Target Devices: 
-- Tool Versions:  GHDL 0.37
-- Description:    skidbuffer for pipelining a bus handshake
-- 
-- Dependencies:   
-- 
-- Revision: 1.0 - Fixed fundamental flaw when m_tready='0' at start of transaction 
-- Revision 0.01 - File Created
-- Additional Comments:
-- 
----------------------------------------------------------------------------------
library ieee;
use ieee.std_logic_1164.all;
use ieee.numeric_std.all;

entity skidbuffer is
  generic (
    DATA_WIDTH  : integer := 32;
    OPT_DATA_REG : boolean := True
  );
  port (
    s_aclk     : in std_logic;
    s_aresetn  : in std_logic;

    s_valid : in  std_logic;
    s_ready : out std_logic;
    s_data  : in  std_logic_vector(DATA_WIDTH - 1 downto 0);

    m_valid : out std_logic;
    m_ready : in  std_logic;
    m_data  : out std_logic_vector(DATA_WIDTH - 1 downto 0)
  );
end skidbuffer;

architecture behav of skidbuffer is
  -- register signals
  signal reg_data  : std_logic_vector(DATA_WIDTH-1 downto 0);
  signal reg_valid : std_logic;
  signal reg_ready : std_logic;

  -- skid buffer signals (only used when OPT_DATA_REG = '1')
  signal skd_data  : std_logic_vector(DATA_WIDTH-1 downto 0);
  signal skd_valid : std_logic;

  -- output signals for output multiplexer
  signal out_data  : std_logic_vector(DATA_WIDTH-1 downto 0);
  signal out_valid : std_logic;

begin
  -- I/O connections assignments
  s_ready <= reg_ready;

  -- ready is always registered in skidbuffer
  p_reg_ready : process(s_aclk)
  begin
    if rising_edge(s_aclk) then 
      if s_aresetn = '0' then
        reg_ready <= '0';
      else
        reg_ready <= m_ready;
      end if;
    end if;
  end process;

  -- output of the skidbuffer (either registered or bypass)
  out_data  <= skd_data  when (reg_ready = '0') else s_data;
  out_valid <= skd_valid when (reg_ready = '0') else s_valid;

  -- actual skidbuffer register
  p_reg : process (s_aclk)
  begin
    if rising_edge(s_aclk) then 
      if s_aresetn = '0' then
        skd_data  <= (others => '0');
        skd_valid <= '0';
      else
        if reg_ready = '1' then
          skd_data <= s_data;
          skd_valid <= s_valid;
        else
          skd_data <= skd_data;
          skd_valid <= skd_valid;
        end if;
      end if;
    end if;
  end process;

-- NOT REGISTERED OUTPUT -------------------------------------------------------
  gen_no_register : if not OPT_DATA_REG generate
    -- output multiplexer
    m_valid <= out_valid;
    m_data  <= out_data;
  end generate;

-- FULLY REGISTERED OUTPUT -----------------------------------------------------
  gen_data_register : if OPT_DATA_REG generate
    process(s_aclk) begin
      if rising_edge(s_aclk) then
        if m_ready = '1' then
          -- if: m_ is ready, continue feeding stream
          m_data <= out_data;
          m_valid <= out_valid; 
          -- else: hold value until m_ acknowledges transaction
        end if;
      end if;
    end process;
  end generate;

end behav;

ghdl/basic/tb_skid.vhd
----------------------------------------------------------------------------------
-- Company:        
-- Engineer:       simon.burkhardt
-- 
-- Create Date:    2023-04-21
-- Design Name:    skid buffer testbench
-- Module Name:    tb_skid - bh
-- Project Name:   
-- Target Devices: 
-- Tool Versions:  GHDL 0.37
-- Description:    
-- 
-- Dependencies:   
-- 
-- Revision:
-- Revision 0.01 - File Created
-- Additional Comments:
-- 
----------------------------------------------------------------------------------

library ieee;
use ieee.std_logic_1164.all;
use ieee.numeric_std.all;

-- this testbench acts as a streaming master, sending bursts of data
-- counting from 1-4

-- the testbench itself acts as a correct streaming master which keeps the data
-- until it is acknowledged by the DUT by asserting tready.

-- the data pattern can be influenced by the user in 2 ways
-- + Tx requests are generated by changing the pattern in p_stimuli_tready
--   the master will try to send data for as long as sim_valid_data = '1'
-- + Rx acknowledgements are generated by changing the pattern in p_stimuli_tready
--   the downstream slave after the DUT will signal ready-to-receive 
--   when sim_ready_data = '1'

-- simulate both with OPT_DATA_REG = True / False
entity tb_skid is
  generic
  (
    DATA_WIDTH   : natural := 8;
    OPT_DATA_REG : boolean := False
  );
end tb_skid;

architecture bh of tb_skid is
  -- DUT component declaration
  component skidbuffer is
    generic (
      DATA_WIDTH   : integer;
      OPT_DATA_REG : boolean
    );
    port (
      s_aclk     : in std_logic;
      s_aresetn  : in std_logic;

      s_valid : in  std_logic;
      s_ready : out std_logic;
      s_data  : in  std_logic_vector(DATA_WIDTH - 1 downto 0);

      m_valid : out std_logic;
      m_ready : in  std_logic;
      m_data  : out std_logic_vector(DATA_WIDTH - 1 downto 0)
    );
  end component;
  
  constant CLK_PERIOD: TIME := 5 ns;

  signal sim_valid_data  : std_logic := '0';
  signal sim_ready_data  : std_logic := '0';
  signal sim_data        : std_logic_vector(DATA_WIDTH-1 downto 0);

  signal s_axis_tvalid : std_logic := '0';
  signal s_axis_tdata  : std_logic_vector(DATA_WIDTH-1 downto 0);
  signal s_axis_tready : std_logic := '0';

  signal m_axis_tvalid : std_logic := '0';
  signal m_axis_tdata  : std_logic_vector(DATA_WIDTH-1 downto 0);
  signal m_axis_tready : std_logic := '0';

  signal clk   : std_logic := '0';
  signal rst_n : std_logic := '0';

  signal clk_count : unsigned(7 downto 0) := (others => '0');

  CONSTANT T_START_BURST_1 : integer := 3;
  CONSTANT T_END_BURST_1 : integer := 3+4+1;
  CONSTANT T_START_BURST_2 : integer := 10;
  CONSTANT T_END_BURST_2 : integer := 10+2+1;
  CONSTANT T_START_BURST_3 : integer := 15;
  CONSTANT T_END_BURST_3 : integer := 15+2+1;
  CONSTANT T_START_BURST_4 : integer := 20;
  CONSTANT T_END_BURST_4 : integer := 20+2;

  CONSTANT T_START_BURST_5 : integer := 30;
  CONSTANT T_END_BURST_5 : integer := 30+2+3;

begin

  -- generate clk signal
  p_clk_gen : process
  begin
   clk <= '1';
   wait for (CLK_PERIOD / 2);
   clk <= '0';
   wait for (CLK_PERIOD / 2);
   clk_count <= clk_count + 1;
  end process;

  -- generate initial reset
  p_reset_gen : process
  begin 
    rst_n <= '0';
    wait until rising_edge(clk);
    wait until rising_edge(clk);
    wait for (CLK_PERIOD / 4);
    rst_n <= '1';
    wait;
  end process;

  -- generate ready signal
  p_stimuli_tready : process(clk)
  begin
    if rising_edge(clk) then
      if rst_n = '0' then
        m_axis_tready <= '0';
      else
        m_axis_tready <= sim_ready_data;
        
        -- not ready, mid burst
        if clk_count = T_START_BURST_1-1 then
          sim_ready_data <= '1';
        end if;
        if clk_count = T_START_BURST_1+1 then
          sim_ready_data <= '0';
        end if;
        if clk_count = T_START_BURST_1+2 then
          sim_ready_data <= '1';
        end if;

        -- hiccup right before burst
        if clk_count = T_START_BURST_2-1 then
          sim_ready_data <= '0';
        end if;
        if clk_count = T_START_BURST_2 then
          sim_ready_data <= '1';
        end if;

        -- hiccup on first burst beat
        if clk_count = T_START_BURST_3 then
          sim_ready_data <= '0';
        end if;
        if clk_count = T_START_BURST_3+1 then
          sim_ready_data <= '1';
        end if;

        -- hiccup after first burst beat
        if clk_count = T_START_BURST_4+1 then
          sim_ready_data <= '0';
        end if;
        if clk_count = T_START_BURST_4+2 then
          sim_ready_data <= '1';
        end if;

        if clk_count = T_START_BURST_5-2 then
          sim_ready_data <= '0';
        end if;
        if clk_count = T_START_BURST_5+3 then
          sim_ready_data <= '1';
        end if;

      end if;
    end if;
  end process;

  -- generate valid signal
  p_stimuli_tvalid : process(clk)
  begin
    if rising_edge(clk) then
      if rst_n = '0' then
        sim_valid_data <= '0';
      else
        -- 4 beats of burst + 1 for not ready
        if clk_count = T_START_BURST_1 then
          sim_valid_data <= '1';
        end if;
        if clk_count = T_END_BURST_1 then
          sim_valid_data <= '0';
        end if;

        -- 2 beats of burst +1 not ready
        if clk_count = T_START_BURST_2 then
          sim_valid_data <= '1';
        end if;
        if clk_count = T_END_BURST_2 then
          sim_valid_data <= '0';
        end if;

        -- 2 beats of burst +1 not ready
        if clk_count = T_START_BURST_3 then
          sim_valid_data <= '1';
        end if;
        if clk_count = T_END_BURST_3 then
          sim_valid_data <= '0';
        end if;

        -- 2 beats of burst +1 not ready
        if clk_count = T_START_BURST_4 then
          sim_valid_data <= '1';
        end if;
        if clk_count = T_END_BURST_4 then
          sim_valid_data <= '0';
        end if;

        if clk_count = T_START_BURST_5 then
          sim_valid_data <= '1';
        end if;
        if clk_count = T_END_BURST_5 then
          sim_valid_data <= '0';
        end if;
      end if;
    end if;
  end process;

  -- generate counter data when successfully acknowledged (tready) by slave
  p_stimuli_tdata : process(clk)
  begin
    if rising_edge(clk) then
      if rst_n = '0' then
        s_axis_tdata <= (others => '0');
        sim_data <= (others => '0');
      else
        if sim_valid_data = '1' then    -- VALID can be controlled
          if s_axis_tready = '1' then   -- READY can be controlled
            if unsigned(s_axis_tdata) = 4 then
              -- restart counter at "1"
              s_axis_tdata(DATA_WIDTH-1 downto 1) <= (others => '0');
              s_axis_tdata(0) <= '1';
              sim_data(DATA_WIDTH-1 downto 1) <= (others => '0');
              sim_data(0) <= '1';
            else
              if (unsigned(sim_data) > unsigned(s_axis_tdata)) and (unsigned(sim_data) < 4) then
                s_axis_tdata <= std_logic_vector(unsigned(sim_data) + 1);
              else
                s_axis_tdata <= std_logic_vector(unsigned(s_axis_tdata) + 1);
              end if;
              
              if unsigned(sim_data) = 4 then
                sim_data(DATA_WIDTH-1 downto 1) <= (others => '0');
                sim_data(0) <= '1';
              else
                sim_data <= std_logic_vector(unsigned(sim_data) + 1);
              end if;
            end if;
          else
            s_axis_tdata <= s_axis_tdata;
            sim_data <= sim_data;
          end if;
          s_axis_tvalid <= '1';
        else 
          s_axis_tvalid <= '0';
          s_axis_tdata <= (others => '0');
          sim_data <= sim_data;
        end if;
      end if;
    end if;
  end process;

-- DUT instance and connections
  skidbuffer_inst : skidbuffer
  generic map (
      DATA_WIDTH   => DATA_WIDTH,
      OPT_DATA_REG => OPT_DATA_REG
  )
  port map (
    s_aclk    => clk,
    s_aresetn => rst_n,

    s_valid => s_axis_tvalid,
    s_ready => s_axis_tready,
    s_data  => s_axis_tdata,

    m_valid => m_axis_tvalid,
    m_ready => m_axis_tready,
    m_data  => m_axis_tdata
  );

end bh;

ghdl/basic/wave.vcd
$date
  Mon Dec 18 17:31:44 2023
$end
$version
  GHDL v0
$end
$timescale
  1 fs
$end
$scope module standard $end
$upscope $end
$scope module std_logic_1164 $end
$upscope $end
$scope module numeric_std $end
$upscope $end
$scope module tb_skid $end
$var reg 1 ! sim_valid_data $end
$var reg 1 " sim_ready_data $end
$var reg 8 # sim_data[7:0] $end
$var reg 1 $ s_axis_tvalid $end
$var reg 8 % s_axis_tdata[7:0] $end
$var reg 1 & s_axis_tready $end
$var reg 1 ' m_axis_tvalid $end
$var reg 8 ( m_axis_tdata[7:0] $end
$var reg 1 ) m_axis_tready $end
$var reg 1 * clk $end
$var reg 1 + rst_n $end
$var reg 8 , clk_count[7:0] $end
$scope module skidbuffer_inst $end
$var reg 1 - s_aclk $end
$var reg 1 . s_aresetn $end
$var reg 1 / s_valid $end
$var reg 1 0 s_ready $end
$var reg 8 1 s_data[7:0] $end
$var reg 1 2 m_valid $end
$var reg 1 3 m_ready $end
$var reg 8 4 m_data[7:0] $end
$var reg 8 5 reg_data[7:0] $end
$var reg 1 6 reg_valid $end
$var reg 1 7 reg_ready $end
$var reg 8 8 skd_data[7:0] $end
$var reg 1 9 skd_valid $end
$var reg 8 : out_data[7:0] $end
$var reg 1 ; out_valid $end
$scope module gen_data_register $end
$upscope $end
$upscope $end
$upscope $end
$enddefinitions $end
#0
0!
1"
bUUUUUUUU #
0$
bUUUUUUUU %
U&
U'
bUUUUUUUU (
0)
1*
0+
b00000000 ,
1-
0.
0/
U0
bUUUUUUUU 1
U2
03
bUUUUUUUU 4
bUUUUUUUU 5
U6
U7
bUUUUUUUU 8
U9
bUUUUUUUU :
0;
#2500000
0*
0-
#5000000
b00000000 #
b00000000 %
0&
1)
1*
b00000001 ,
1-
00
b00000000 1
13
07
b00000000 8
09
b00000000 :
#6250000
1+
1.
#7500000
0*
0-
#10000000
1&
0'
b00000000 (
1*
b00000010 ,
1-
10
02
b00000000 4
17
#12500000
0*
0-
#15000000
1!
1*
b00000011 ,
1-
#17500000
0*
0-
#20000000
0"
b00000001 #
1$
b00000001 %
1*
b00000100 ,
1-
1/
b00000001 1
b00000001 :
1;
#22500000
0*
0-
#25000000
1"
b00000010 #
b00000010 %
1'
b00000001 (
0)
1*
b00000101 ,
1-
b00000010 1
12
03
b00000001 4
b00000001 8
19
b00000010 :
#27500000
0*
0-
#30000000
b00000011 #
b00000011 %
0&
1)
1*
b00000110 ,
1-
00
b00000011 1
13
07
b00000010 8
#32500000
0*
0-
#35000000
1&
b00000010 (
1*
b00000111 ,
1-
10
b00000010 4
17
b00000011 :
#37500000
0*
0-
#40000000
0!
b00000100 #
b00000100 %
b00000011 (
1*
b00001000 ,
1-
b00000100 1
b00000011 4
b00000011 8
b00000100 :
#42500000
0*
0-
#45000000
0"
0$
b00000000 %
b00000100 (
1*
b00001001 ,
1-
0/
b00000000 1
b00000100 4
b00000100 8
b00000000 :
0;
#47500000
0*
0-
#50000000
1!
1"
0'
b00000000 (
0)
1*
b00001010 ,
1-
02
03
b00000000 4
b00000000 8
09
#52500000
0*
0-
#55000000
b00000001 #
1$
b00000001 %
0&
1)
1*
b00001011 ,
1-
1/
00
b00000001 1
13
07
#57500000
0*
0-
#60000000
1&
1*
b00001100 ,
1-
10
17
b00000001 :
1;
#62500000
0*
0-
#65000000
0!
b00000010 #
b00000010 %
1'
b00000001 (
1*
b00001101 ,
1-
b00000010 1
12
b00000001 4
b00000001 8
19
b00000010 :
#67500000
0*
0-
#70000000
0$
b00000000 %
b00000010 (
1*
b00001110 ,
1-
0/
b00000000 1
b00000010 4
b00000010 8
b00000000 :
0;
#72500000
0*
0-
#75000000
1!
0"
0'
b00000000 (
1*
b00001111 ,
1-
02
b00000000 4
b00000000 8
09
#77500000
0*
0-
#80000000
1"
b00000011 #
1$
b00000011 %
0)
1*
b00010000 ,
1-
1/
b00000011 1
03
b00000011 :
1;
#82500000
0*
0-
#85000000
b00000100 #
b00000100 %
0&
1)
1*
b00010001 ,
1-
00
b00000100 1
13
07
b00000011 8
19
#87500000
0*
0-
#90000000
0!
1&
1'
b00000011 (
1*
b00010010 ,
1-
10
12
b00000011 4
17
b00000100 :
#92500000
0*
0-
#95000000
0$
b00000000 %
b00000100 (
1*
b00010011 ,
1-
0/
b00000000 1
b00000100 4
b00000100 8
b00000000 :
0;
#97500000
0*
0-
#100000000
1!
0'
b00000000 (
1*
b00010100 ,
1-
02
b00000000 4
b00000000 8
09
#102500000
0*
0-
#105000000
0"
b00000001 #
1$
b00000001 %
1*
b00010101 ,
1-
1/
b00000001 1
b00000001 :
1;
#107500000
0*
0-
#110000000
0!
1"
b00000010 #
b00000010 %
1'
b00000001 (
0)
1*
b00010110 ,
1-
b00000010 1
12
03
b00000001 4
b00000001 8
19
b00000010 :
#112500000
0*
0-
#115000000
0$
b00000000 %
0&
1)
1*
b00010111 ,
1-
0/
00
b00000000 1
13
07
b00000010 8
#117500000
0*
0-
#120000000
1&
b00000010 (
1*
b00011000 ,
1-
10
b00000010 4
17
b00000000 :
0;
#122500000
0*
0-
#125000000
0'
b00000000 (
1*
b00011001 ,
1-
02
b00000000 4
b00000000 8
09
#127500000
0*
0-
#130000000
1*
b00011010 ,
1-
#132500000
0*
0-
#135000000
1*
b00011011 ,
1-
#137500000
0*
0-
#140000000
1*
b00011100 ,
1-
#142500000
0*
0-
#145000000
1*
b00011101 ,
1-
#147500000
0*
0-
#150000000
1*
b00011110 ,
1-
#152500000
0*
0-
#155000000
1*
b00011111 ,
1-
#157500000
0*
0-
#160000000
1*
b00100000 ,
1-
#162500000
0*
0-
#165000000
1*
b00100001 ,
1-
#167500000
0*
0-
#170000000
1*
b00100010 ,
1-
#172500000
0*
0-
#175000000
1*
b00100011 ,
1-
#177500000
0*
0-
#180000000
1*
b00100100 ,
1-
#182500000
0*
0-
#185000000
1*
b00100101 ,
1-
#187500000
0*
0-
#190000000
1*
b00100110 ,
1-
#192500000
0*
0-
#195000000
1*
b00100111 ,
1-
#197500000
0*
0-
#200000000
1*
b00101000 ,
1-
#202500000
0*
0-
#205000000
1*
b00101001 ,
1-
#207500000
0*
0-
#210000000
1*
b00101010 ,
1-
#212500000
0*
0-
#215000000
1*
b00101011 ,
1-
#217500000
0*
0-
#220000000
1*
b00101100 ,
1-
#222500000
0*
0-
#225000000
1*
b00101101 ,
1-
#227500000
0*
0-
#230000000
1*
b00101110 ,
1-
#232500000
0*
0-
#235000000
1*
b00101111 ,
1-
#237500000
0*
0-
#240000000
1*
b00110000 ,
1-
#242500000
0*
0-
#245000000
1*
b00110001 ,
1-
#247500000
0*
0-
#250000000
1*
b00110010 ,
1-
#252500000
0*
0-
#255000000
1*
b00110011 ,
1-
#257500000
0*
0-
#260000000
1*
b00110100 ,
1-
#262500000
0*
0-
#265000000
1*
b00110101 ,
1-
#267500000
0*
0-
#270000000
1*
b00110110 ,
1-
#272500000
0*
0-
#275000000
1*
b00110111 ,
1-
#277500000
0*
0-
#280000000
1*
b00111000 ,
1-
#282500000
0*
0-
#285000000
1*
b00111001 ,
1-
#287500000
0*
0-
#290000000
1*
b00111010 ,
1-
#292500000
0*
0-
#295000000
1*
b00111011 ,
1-
#297500000
0*
0-
#300000000
1*
b00111100 ,
1-
#302500000
0*
0-
#305000000
1*
b00111101 ,
1-
#307500000
0*
0-
#310000000
1*
b00111110 ,
1-
#312500000
0*
0-
#315000000
1*
b00111111 ,
1-
#317500000
0*
0-
#320000000
1*
b01000000 ,
1-
#322500000
0*
0-
#325000000
1*
b01000001 ,
1-
#327500000
0*
0-
#330000000
1*
b01000010 ,
1-
#332500000
0*
0-
#335000000
1*
b01000011 ,
1-
#337500000
0*
0-
#340000000
1*
b01000100 ,
1-
#342500000
0*
0-
#345000000
1*
b01000101 ,
1-
#347500000
0*
0-
#350000000
1*
b01000110 ,
1-
#352500000
0*
0-
#355000000
1*
b01000111 ,
1-
#357500000
0*
0-
#360000000
1*
b01001000 ,
1-
#362500000
0*
0-
#365000000
1*
b01001001 ,
1-
#367500000
0*
0-
#370000000
1*
b01001010 ,
1-
#372500000
0*
0-
#375000000
1*
b01001011 ,
1-
#377500000
0*
0-
#380000000
1*
b01001100 ,
1-
#382500000
0*
0-
#385000000
1*
b01001101 ,
1-
#387500000
0*
0-
#390000000
1*
b01001110 ,
1-
#392500000
0*
0-
#395000000
1*
b01001111 ,
1-
#397500000
0*
0-
#400000000
1*
b01010000 ,
1-
#402500000
0*
0-
#405000000
1*
b01010001 ,
1-
#407500000
0*
0-
#410000000
1*
b01010010 ,
1-
#412500000
0*
0-
#415000000
1*
b01010011 ,
1-
#417500000
0*
0-
#420000000
1*
b01010100 ,
1-
#422500000
0*
0-
#425000000
1*
b01010101 ,
1-
#427500000
0*
0-
#430000000
1*
b01010110 ,
1-
#432500000
0*
0-
#435000000
1*
b01010111 ,
1-
#437500000
0*
0-
#440000000
1*
b01011000 ,
1-
#442500000
0*
0-
#445000000
1*
b01011001 ,
1-
#447500000
0*
0-
#450000000
1*
b01011010 ,
1-
#452500000
0*
0-
#455000000
1*
b01011011 ,
1-
#457500000
0*
0-
#460000000
1*
b01011100 ,
1-
#462500000
0*
0-
#465000000
1*
b01011101 ,
1-
#467500000
0*
0-
#470000000
1*
b01011110 ,
1-
#472500000
0*
0-
#475000000
1*
b01011111 ,
1-
#477500000
0*
0-
#480000000
1*
b01100000 ,
1-
#482500000
0*
0-
#485000000
1*
b01100001 ,
1-
#487500000
0*
0-
#490000000
1*
b01100010 ,
1-
#492500000
0*
0-
#495000000
1*
b01100011 ,
1-
#497500000
0*
0-
#500000000
1*
b01100100 ,
1-
#502500000
0*
0-
#505000000
1*
b01100101 ,
1-
#507500000
0*
0-
#510000000
1*
b01100110 ,
1-
#512500000
0*
0-
#515000000
1*
b01100111 ,
1-
#517500000
0*
0-
#520000000
1*
b01101000 ,
1-
#522500000
0*
0-
#525000000
1*
b01101001 ,
1-
#527500000
0*
0-
#530000000
1*
b01101010 ,
1-
#532500000
0*
0-
#535000000
1*
b01101011 ,
1-
#537500000
0*
0-
#540000000
1*
b01101100 ,
1-
#542500000
0*
0-
#545000000
1*
b01101101 ,
1-
#547500000
0*
0-
#550000000
1*
b01101110 ,
1-
#552500000
0*
0-
#555000000
1*
b01101111 ,
1-
#557500000
0*
0-
#560000000
1*
b01110000 ,
1-
#562500000
0*
0-
#565000000
1*
b01110001 ,
1-
#567500000
0*
0-
#570000000
1*
b01110010 ,
1-
#572500000
0*
0-
#575000000
1*
b01110011 ,
1-
#577500000
0*
0-
#580000000
1*
b01110100 ,
1-
#582500000
0*
0-
#585000000
1*
b01110101 ,
1-
#587500000
0*
0-
#590000000
1*
b01110110 ,
1-
#592500000
0*
0-
#595000000
1*
b01110111 ,
1-
#597500000
0*
0-
#600000000
1*
b01111000 ,
1-
#602500000
0*
0-
#605000000
1*
b01111001 ,
1-
#607500000
0*
0-
#610000000
1*
b01111010 ,
1-
#612500000
0*
0-
#615000000
1*
b01111011 ,
1-
#617500000
0*
0-
#620000000
1*
b01111100 ,
1-
#622500000
0*
0-
#625000000
1*
b01111101 ,
1-
#627500000
0*
0-
#630000000
1*
b01111110 ,
1-
#632500000
0*
0-
#635000000
1*
b01111111 ,
1-
#637500000
0*
0-
#640000000
1*
b10000000 ,
1-
#642500000
0*
0-
#645000000
1*
b10000001 ,
1-
#647500000
0*
0-
#650000000
1*
b10000010 ,
1-
#652500000
0*
0-
#655000000
1*
b10000011 ,
1-
#657500000
0*
0-
#660000000
1*
b10000100 ,
1-
#662500000
0*
0-
#665000000
1*
b10000101 ,
1-
#667500000
0*
0-
#670000000
1*
b10000110 ,
1-
#672500000
0*
0-
#675000000
1*
b10000111 ,
1-
#677500000
0*
0-
#680000000
1*
b10001000 ,
1-
#682500000
0*
0-
#685000000
1*
b10001001 ,
1-
#687500000
0*
0-
#690000000
1*
b10001010 ,
1-
#692500000
0*
0-
#695000000
1*
b10001011 ,
1-
#697500000
0*
0-
#700000000
1*
b10001100 ,
1-
#702500000
0*
0-
#705000000
1*
b10001101 ,
1-
#707500000
0*
0-
#710000000
1*
b10001110 ,
1-
#712500000
0*
0-
#715000000
1*
b10001111 ,
1-
#717500000
0*
0-
#720000000
1*
b10010000 ,
1-
#722500000
0*
0-
#725000000
1*
b10010001 ,
1-
#727500000
0*
0-
#730000000
1*
b10010010 ,
1-
#732500000
0*
0-
#735000000
1*
b10010011 ,
1-
#737500000
0*
0-
#740000000
1*
b10010100 ,
1-
#742500000
0*
0-
#745000000
1*
b10010101 ,
1-
#747500000
0*
0-
#750000000
1*
b10010110 ,
1-
#752500000
0*
0-
#755000000
1*
b10010111 ,
1-
#757500000
0*
0-
#760000000
1*
b10011000 ,
1-
#762500000
0*
0-
#765000000
1*
b10011001 ,
1-
#767500000
0*
0-
#770000000
1*
b10011010 ,
1-
#772500000
0*
0-
#775000000
1*
b10011011 ,
1-
#777500000
0*
0-
#780000000
1*
b10011100 ,
1-
#782500000
0*
0-
#785000000
1*
b10011101 ,
1-
#787500000
0*
0-
#790000000
1*
b10011110 ,
1-
#792500000
0*
0-
#795000000
1*
b10011111 ,
1-
#797500000
0*
0-
#800000000
1*
b10100000 ,
1-
#802500000
0*
0-
#805000000
1*
b10100001 ,
1-
#807500000
0*
0-
#810000000
1*
b10100010 ,
1-
#812500000
0*
0-
#815000000
1*
b10100011 ,
1-
#817500000
0*
0-
#820000000
1*
b10100100 ,
1-
#822500000
0*
0-
#825000000
1*
b10100101 ,
1-
#827500000
0*
0-
#830000000
1*
b10100110 ,
1-
#832500000
0*
0-
#835000000
1*
b10100111 ,
1-
#837500000
0*
0-
#840000000
1*
b10101000 ,
1-
#842500000
0*
0-
#845000000
1*
b10101001 ,
1-
#847500000
0*
0-
#850000000
1*
b10101010 ,
1-
#852500000
0*
0-
#855000000
1*
b10101011 ,
1-
#857500000
0*
0-
#860000000
1*
b10101100 ,
1-
#862500000
0*
0-
#865000000
1*
b10101101 ,
1-
#867500000
0*
0-
#870000000
1*
b10101110 ,
1-
#872500000
0*
0-
#875000000
1*
b10101111 ,
1-
#877500000
0*
0-
#880000000
1*
b10110000 ,
1-
#882500000
0*
0-
#885000000
1*
b10110001 ,
1-
#887500000
0*
0-
#890000000
1*
b10110010 ,
1-
#892500000
0*
0-
#895000000
1*
b10110011 ,
1-
#897500000
0*
0-
#900000000
1*
b10110100 ,
1-
#902500000
0*
0-
#905000000
1*
b10110101 ,
1-
#907500000
0*
0-
#910000000
1*
b10110110 ,
1-
#912500000
0*
0-
#915000000
1*
b10110111 ,
1-
#917500000
0*
0-
#920000000
1*
b10111000 ,
1-
#922500000
0*
0-
#925000000
1*
b10111001 ,
1-
#927500000
0*
0-
#930000000
1*
b10111010 ,
1-
#932500000
0*
0-
#935000000
1*
b10111011 ,
1-
#937500000
0*
0-
#940000000
1*
b10111100 ,
1-
#942500000
0*
0-
#945000000
1*
b10111101 ,
1-
#947500000
0*
0-
#950000000
1*
b10111110 ,
1-
#952500000
0*
0-
#955000000
1*
b10111111 ,
1-
#957500000
0*
0-
#960000000
1*
b11000000 ,
1-
#962500000
0*
0-
#965000000
1*
b11000001 ,
1-
#967500000
0*
0-
#970000000
1*
b11000010 ,
1-
#972500000
0*
0-
#975000000
1*
b11000011 ,
1-
#977500000
0*
0-
#980000000
1*
b11000100 ,
1-
#982500000
0*
0-
#985000000
1*
b11000101 ,
1-
#987500000
0*
0-
#990000000
1*
b11000110 ,
1-
#992500000
0*
0-
#995000000
1*
b11000111 ,
1-
#997500000
0*
0-
#1000000000
1*
b11001000 ,
1-
