vhdl/axis-dsp-concept/skidbuffer.vhd
----------------------------------------------------------------------------------
-- Company:        
-- Engineer:       simon.burkhardt
-- 
-- Create Date:    2023-04-21
-- Design Name:    AXIS skidbuffer
-- Module Name:    tb_skid - bh
-- Project Name:   
-- Target Devices: 
-- Tool Versions:  GHDL 0.37
-- Description:    skidbuffer for pipelining a bus handshake
-- 
-- Dependencies:   
-- 
-- Revision:
-- Revision 0.01 - File Created
-- Additional Comments:
-- 
----------------------------------------------------------------------------------
library ieee;
use ieee.std_logic_1164.all;
use ieee.numeric_std.all;

entity skidbuffer is
  generic (
    DATA_WIDTH  : integer := 32;
    OPT_DATA_REG : boolean := True
  );
  port (
    clock     : in std_logic;
    reset_n   : in std_logic;

    s_valid_i : in  std_logic;
    s_last_i  : in  std_logic;
    s_ready_o : out std_logic;
    s_data_i  : in  std_logic_vector(DATA_WIDTH - 1 downto 0);

    m_valid_o : out std_logic;
    m_last_o  : out std_logic;
    m_ready_i : in  std_logic;
    m_data_o  : out std_logic_vector(DATA_WIDTH - 1 downto 0)
  );
end skidbuffer;

architecture arch_imp of skidbuffer is
  -- register signals
  signal reg_data  : std_logic_vector(DATA_WIDTH-1 downto 0) := (others => '0');
  signal reg_last  : std_logic := '0';
  signal reg_valid : std_logic := '0';
  signal reg_ready : std_logic := '0';

  -- skid buffer signals (only used when OPT_DATA_REG = '1')
  signal skd_data  : std_logic_vector(DATA_WIDTH-1 downto 0) := (others => '0');
  signal skd_last  : std_logic := '0';

  -- output signals for output multiplexer
  signal out_data  : std_logic_vector(DATA_WIDTH-1 downto 0) := (others => '0');
  signal out_last  : std_logic := '0';

begin
  -- I/O connections assignments
  m_valid_o <= reg_valid;
  s_ready_o <= reg_ready;
  m_data_o  <= out_data;
  m_last_o  <= out_last;

  -- ready is always registered
  p_reg_ready : process(clock)
  begin
    if rising_edge(clock) then 
      if reset_n = '0' then
        reg_ready <= '0';
      else
        reg_ready <= m_ready_i;
      end if;
    end if;
  end process;

-- NOT REGISTERED OUTPUT -------------------------------------------------------
  gen_no_register : if not OPT_DATA_REG generate
    reg_valid <= s_valid_i; -- valid is not registered
    -- output multiplexer
    out_data <= reg_data when (reg_ready = '0') else s_data_i;
    out_last <= reg_last when (reg_ready = '0') else s_last_i;

    p_reg : process (clock)
    begin
      if rising_edge(clock) then 
        if reset_n = '0' then
          reg_data  <= (others => '0');
          reg_last  <= '0';
        else
          if reg_ready = '1' then
            reg_data <= s_data_i;
            reg_last <= s_last_i;
          else
            reg_data <= reg_data;
            reg_last <= reg_last;
          end if;
        end if;
      end if;
    end process;
    
  end generate;

-- FULLY REGISTERED OUTPUT -----------------------------------------------------
  gen_data_register : if OPT_DATA_REG generate
    out_data <= reg_data;
    out_last <= reg_last;
    -- registered output signals
    p_reg : process (clock)
    begin
      if rising_edge(clock) then 
        if reset_n = '0' then
          reg_data  <= (others => '0');
          reg_last  <= '0';
          skd_data  <= (others => '0');
          skd_last  <= '0';
          reg_valid <= '0';
        else
          reg_valid <= s_valid_i;
          if reg_ready = '1' then
            skd_data <= s_data_i;
            skd_last <= s_last_i;
          else
            skd_data <= skd_data;
            skd_last <= skd_last;
          end if;

          if m_ready_i = '0' then
            reg_data <= reg_data;
            reg_last <= reg_last;
          else
            if reg_ready = '1' then
              reg_data <= s_data_i;
              reg_last <= s_last_i;
            else
              reg_data <= skd_data;
              reg_last <= skd_last;
            end if;
          end if;
        end if;
      end if;
    end process;
  end generate;

end arch_imp;

ghdl/axis-flow-control/axis_flow_control.vhd
----------------------------------------------------------------------------------
-- Company:        
-- Engineer:       simon.burkhardt
-- 
-- Create Date:    2023-06-21
-- Design Name:    AXIS Flow Control
-- Module Name:    axis_flow_control - bh
-- Project Name:   
-- Target Devices: 
-- Tool Versions:  GHDL 0.37
-- Description:    bidirectional AXIS pipeline register
-- 
-- Dependencies:   
-- 
-- Revision:
-- Revision 0.01 - File Created
-- Additional Comments:
-- 
----------------------------------------------------------------------------------
library ieee;
use ieee.std_logic_1164.all;
use ieee.numeric_std.all;

entity axis_flow_control is
  generic (
    -- Users to add parameters here

    -- User parameters ends
    -- Do not modify the parameters beyond this line

    -- Width of S_AXIS address bus. The slave accepts the read and write addresses of width C_S_AXIS_TDATA_WIDTH.
    C_S_AXIS_TDATA_WIDTH  : integer := 32
  );
  port (
    -- Users to add ports here

    -- User ports ends
    -- Global ports
    AXIS_ACLK : in std_logic;
    AXIS_ARESETN  : in std_logic;

    -- Slave Stream Ports. TVALID indicates that the master is driving a valid transfer, A transfer takes place when both TVALID and TREADY are asserted. 
    S_AXIS_TVALID : in  std_logic;
    -- TDATA is the primary payload that is used to provide the data that is passing across the interface from the master.
    S_AXIS_TDATA  : in  std_logic_vector(C_S_AXIS_TDATA_WIDTH-1 downto 0);
    -- TSTRB is the byte qualifier that indicates whether the content of the associated byte of TDATA is processed as a data byte or a position byte.
    S_AXIS_TSTRB  : in  std_logic_vector((C_S_AXIS_TDATA_WIDTH/8)-1 downto 0);
    -- TLAST indicates the boundary of a packet.
    S_AXIS_TLAST  : in  std_logic;
    -- TREADY indicates that the slave can accept a transfer in the current cycle.
    S_AXIS_TREADY : out std_logic;

    -- Master Stream Ports. TVALID indicates that the master is driving a valid transfer, A transfer takes place when both TVALID and TREADY are asserted. 
    M_AXIS_TVALID : out std_logic;
    -- TDATA is the primary payload that is used to provide the data that is passing across the interface from the master.
    M_AXIS_TDATA  : out std_logic_vector(C_S_AXIS_TDATA_WIDTH-1 downto 0);
    -- TSTRB is the byte qualifier that indicates whether the content of the associated byte of TDATA is processed as a data byte or a position byte.
    M_AXIS_TSTRB  : out std_logic_vector((C_S_AXIS_TDATA_WIDTH/8)-1 downto 0);
    -- TLAST indicates the boundary of a packet.
    M_AXIS_TLAST  : out std_logic;
    -- TREADY indicates that the slave can accept a transfer in the current cycle.
    M_AXIS_TREADY : in  std_logic;

    xon  : in std_logic;
    xoff : in std_logic
  );
end axis_flow_control;

architecture arch_imp of axis_flow_control is
  -- skidbuffer component
  component skidbuffer is
  generic (
    DATA_WIDTH   : natural;
    OPT_DATA_REG : boolean);
    port (
       clock     : in  std_logic;
       reset_n   : in  std_logic;

       s_valid_i : in  std_logic;
       s_last_i  : in  std_logic;
       s_ready_o : out std_logic;
       s_data_i  : in  std_logic_vector((C_S_AXIS_TDATA_WIDTH+(C_S_AXIS_TDATA_WIDTH/8)) - 1 downto 0);

       m_valid_o : out std_logic;
       m_last_o  : out std_logic;
       m_ready_i : in  std_logic;
       m_data_o  : out std_logic_vector((C_S_AXIS_TDATA_WIDTH+(C_S_AXIS_TDATA_WIDTH/8)) - 1 downto 0));
  end component;

  -- signals
  signal aclk    : std_logic;
  signal aresetn : std_logic;

  signal i_s_axis_tvalid : std_logic := '0';
  signal i_s_axis_tdata  : std_logic_vector(C_S_AXIS_TDATA_WIDTH-1 downto 0);
  signal i_axis_data_strb  : std_logic_vector(C_S_AXIS_TDATA_WIDTH+(C_S_AXIS_TDATA_WIDTH/8)-1 downto 0);
  signal i_s_axis_tstrb  : std_logic_vector((C_S_AXIS_TDATA_WIDTH/8)-1 downto 0);
  signal i_s_axis_tlast  : std_logic;
  signal o_s_axis_tready : std_logic;

  signal o_m_axis_tvalid : std_logic;
  signal o_m_axis_tdata  : std_logic_vector(C_S_AXIS_TDATA_WIDTH-1 downto 0);
  signal o_axis_data_strb  : std_logic_vector(C_S_AXIS_TDATA_WIDTH+(C_S_AXIS_TDATA_WIDTH/8)-1 downto 0);
  signal o_m_axis_tstrb  : std_logic_vector((C_S_AXIS_TDATA_WIDTH/8)-1 downto 0);
  signal o_m_axis_tlast  : std_logic;
  signal i_m_axis_tready : std_logic := '0';

  signal en_tready : std_logic;
  signal tready_buf : std_logic;

begin
  -- I/O connections assignments
  aclk    <= AXIS_ACLK;
  aresetn <= AXIS_ARESETN;

  -- inputs
  i_m_axis_tready <= M_AXIS_TREADY;
  i_s_axis_tvalid <= S_AXIS_TVALID;
  i_s_axis_tdata  <= S_AXIS_TDATA;
  i_s_axis_tstrb  <= S_AXIS_TSTRB;
  i_s_axis_tlast  <= S_AXIS_TLAST;

  -- outputs
  S_AXIS_TREADY <= o_s_axis_tready;
  M_AXIS_TVALID <= o_m_axis_tvalid;
  M_AXIS_TDATA  <= o_m_axis_tdata;
  M_AXIS_TSTRB  <= o_m_axis_tstrb;
  M_AXIS_TLAST  <= o_m_axis_tlast;

  -- combine strobe and data signals into single "data" channel
  i_axis_data_strb <= s_axis_tdata & s_axis_tstrb;
  o_m_axis_tdata <= o_axis_data_strb( (C_S_AXIS_TDATA_WIDTH+(C_S_AXIS_TDATA_WIDTH/8)) - 1 downto (C_S_AXIS_TDATA_WIDTH/8) );
  o_m_axis_tstrb <= o_axis_data_strb( (C_S_AXIS_TDATA_WIDTH/8) - 1 downto 0 );

  -- tready is only allowed to be '1' if downstream M port is ready AND if the buffer is in XON condition
  tready_buf <= en_tready and i_m_axis_tready;

  p_en_tready : process(aclk)
  begin
    if rising_edge(aclk) then
      if aresetn = '0' then
        en_tready <= '0';
      else
        if en_tready = '0' then
          if xon = '1' then
            en_tready <= '1';
          end if;
        else
          if xoff = '1' then
            en_tready <= '0';
          end if;
        end if;
      end if;
    end if;
  end process;

  skidbuffer_inst : skidbuffer
  generic map (
      DATA_WIDTH    => (C_S_AXIS_TDATA_WIDTH+(C_S_AXIS_TDATA_WIDTH/8)),
      OPT_DATA_REG  => True
  )
  port map (
    clock     => aclk,
    reset_n   => aresetn,

    s_valid_i => i_s_axis_tvalid,
    s_last_i  => i_s_axis_tlast,
    s_ready_o => o_s_axis_tready,
    s_data_i  => i_axis_data_strb,

    m_valid_o => o_m_axis_tvalid,
    m_last_o  => o_m_axis_tlast,
    m_ready_i => tready_buf,
    m_data_o  => o_axis_data_strb
  );

end arch_imp;

ghdl/axis-flow-control/tb_axis.vhd
----------------------------------------------------------------------------------
-- Company:        
-- Engineer:       simon.burkhardt
-- 
-- Create Date:    2023-04-21
-- Design Name:    skid buffer testbench
-- Module Name:    tb_axis - bh
-- Project Name:   
-- Target Devices: 
-- Tool Versions:  GHDL 0.37
-- Description:    
-- 
-- Dependencies:   
-- 
-- Revision:
-- Revision 0.01 - File Created
-- Additional Comments:
-- 
----------------------------------------------------------------------------------

library ieee;
use ieee.std_logic_1164.all;
use ieee.numeric_std.all;

-- this testbench acts as a streaming master, sending bursts of data
-- counting from 1-4, also asserting tlast on the 4th data packet

-- the testbench itself acts as a correct streaming master which keeps the data
-- until it is acknowledged by the DUT by asserting tready.

-- the data pattern can be influenced by the user in 2 ways
-- + Tx requests are generated by changing the pattern in p_stimuli_tready
--   the master will try to send data for as long as sim_valid_data = '1'
-- + Rx acknowledgements are generated by changing the pattern in p_stimuli_tready
--   the downstream slave after the DUT will signal ready-to-receive 
--   when sim_ready_data = '1'

-- simulate both with OPT_DATA_REG = True / False
entity tb_axis is
  generic
  (
    DATA_WIDTH   : natural := 8;
    OPT_DATA_REG : boolean := True
  );
end tb_axis;

architecture bh of tb_axis is
  -- DUT component declaration
  component axis_flow_control is
    generic (
      C_S_AXIS_TDATA_WIDTH  : integer := 32
    );
    port (
      AXIS_ACLK : in std_logic;
      AXIS_ARESETN  : in std_logic;
 
      S_AXIS_TVALID : in  std_logic;
      S_AXIS_TDATA  : in  std_logic_vector(C_S_AXIS_TDATA_WIDTH-1 downto 0);
      S_AXIS_TSTRB  : in  std_logic_vector((C_S_AXIS_TDATA_WIDTH/8)-1 downto 0);
      S_AXIS_TLAST  : in  std_logic;
      S_AXIS_TREADY : out std_logic;
 
      M_AXIS_TVALID : out std_logic;
      M_AXIS_TDATA  : out std_logic_vector(C_S_AXIS_TDATA_WIDTH-1 downto 0);
      M_AXIS_TSTRB  : out std_logic_vector((C_S_AXIS_TDATA_WIDTH/8)-1 downto 0);
      M_AXIS_TLAST  : out std_logic;
      M_AXIS_TREADY : in  std_logic;

      xon  : in std_logic;
      xoff : in std_logic
    );
  end component;
  
  constant CLK_PERIOD: TIME := 5 ns;

  signal sim_valid_data  : std_logic := '0';
  signal sim_ready_data  : std_logic := '1';
  signal sim_data        : std_logic_vector(DATA_WIDTH-1 downto 0);

  signal s_axis_tvalid : std_logic := '0';
  signal s_axis_tdata  : std_logic_vector(DATA_WIDTH-1 downto 0);
  signal s_axis_tstrb  : std_logic_vector((DATA_WIDTH/8)-1 downto 0);
  signal s_axis_tlast  : std_logic;
  signal s_axis_tready : std_logic;

  signal m_axis_tvalid : std_logic;
  signal m_axis_tdata  : std_logic_vector(DATA_WIDTH-1 downto 0);
  signal m_axis_tstrb  : std_logic_vector((DATA_WIDTH/8)-1 downto 0);
  signal m_axis_tlast  : std_logic;
  signal m_axis_tready : std_logic := '0';

  signal fifo_full  : std_logic;
  signal fifo_empty : std_logic;

  signal clk   : std_logic;
  signal rst_n : std_logic;

  signal clk_count : std_logic_vector(7 downto 0) := (others => '0');
begin

  -- generate clk signal
  p_clk_gen : process
  begin
   clk <= '1';
   wait for (CLK_PERIOD / 2);
   clk <= '0';
   wait for (CLK_PERIOD / 2);
   clk_count <= std_logic_vector(unsigned(clk_count) + 1);
  end process;

  -- generate initial reset
  p_reset_gen : process
  begin 
    rst_n <= '0';
    wait until rising_edge(clk);
    wait for (CLK_PERIOD / 4);
    rst_n <= '1';
    wait;
  end process;

  -- generate ready signal
  p_stimuli_fifo : process(clk)
  begin
    if rising_edge(clk) then
      if rst_n = '0' then
        fifo_full <= '0';
        fifo_empty <= '1';
      else
        if unsigned(clk_count) = 40 then
          fifo_empty <= '0';
        end if;
        if unsigned(clk_count) = 48 then
          fifo_full <= '1';
        end if;
        if unsigned(clk_count) = 58 then
          fifo_full <= '0';
        end if;
        if unsigned(clk_count) = 65 then
          fifo_empty <= '1';
        end if;

      end if;
    end if;
  end process;

  -- generate ready signal
  p_stimuli_tready : process(clk)
  begin
    if rising_edge(clk) then
      if rst_n = '0' then
        m_axis_tready <= '1';
      else
        m_axis_tready <= sim_ready_data;
        if unsigned(clk_count) = 2 then
          sim_ready_data <= '1';
        end if;
        if unsigned(clk_count) = 7 then
          sim_ready_data <= '0';
        end if;
        if unsigned(clk_count) = 8 then
          sim_ready_data <= '1';
        end if;
        if unsigned(clk_count) = 11 then
          sim_ready_data <= '0';
        end if;
        if unsigned(clk_count) = 13 then
          sim_ready_data <= '1';
        end if;
        if unsigned(clk_count) = 14 then
          sim_ready_data <= '0';
        end if;
        if unsigned(clk_count) = 15 then
          sim_ready_data <= '1';
        end if;
      end if;
    end if;
  end process;

  -- generate valid signal
  p_stimuli_tvalid : process(clk)
  begin
    if rising_edge(clk) then
      if rst_n = '0' then
        sim_valid_data <= '0';
      else
        if unsigned(clk_count) = 2 then
          sim_valid_data <= '1';
        end if;
        if unsigned(clk_count) = 18 then
          sim_valid_data <= '0';
        end if;
        if unsigned(clk_count) = 21 then
          sim_valid_data <= '1';
        end if;
        if unsigned(clk_count) = 23 then
          sim_valid_data <= '0';
        end if;
        if unsigned(clk_count) = 24 then
          sim_valid_data <= '1';
        end if;
        if unsigned(clk_count) = 26 then
          sim_valid_data <= '0';
        end if;

        if unsigned(clk_count) = 32 then
          sim_valid_data <= '1';
        end if;
      end if;
    end if;
  end process;

  -- generate counter data when successfully acknowledged (tready) by slave
  p_stimuli_tdata : process(clk)
  begin
    if rising_edge(clk) then
      if rst_n = '0' then
        s_axis_tdata <= (others => '0');
        s_axis_tstrb <= (others => '0');
        sim_data <= (others => '0');
        s_axis_tlast <= '0';
      else
        if sim_valid_data = '1' then    -- VALID can be controlled
          if s_axis_tready = '1' then   -- READY can be controlled
            if unsigned(s_axis_tdata) = 3 then
              s_axis_tlast <= '1';
            else 
              s_axis_tlast <= '0';
            end if;

            if unsigned(s_axis_tdata) = 4 then
              -- restart counter at "1"
              s_axis_tdata(DATA_WIDTH-1 downto 1) <= (others => '0');
              s_axis_tdata(0) <= '1';
              sim_data(DATA_WIDTH-1 downto 1) <= (others => '0');
              sim_data(0) <= '1';
            else
              if (unsigned(sim_data) > unsigned(s_axis_tdata)) and (unsigned(sim_data) < 4) then
                s_axis_tdata <= std_logic_vector(unsigned(sim_data) + 1);
              else
                s_axis_tdata <= std_logic_vector(unsigned(s_axis_tdata) + 1);
              end if;
              
              if unsigned(sim_data) = 4 then
                sim_data(DATA_WIDTH-1 downto 1) <= (others => '0');
                sim_data(0) <= '1';
              else
                sim_data <= std_logic_vector(unsigned(sim_data) + 1);
              end if;
            end if;
          else
            s_axis_tdata <= s_axis_tdata;
            sim_data <= sim_data;
          end if;
          s_axis_tvalid <= '1';
          s_axis_tstrb <= "1";
        else 
          s_axis_tvalid <= '0';
          s_axis_tstrb <= "0";
          s_axis_tlast <= '0';
          s_axis_tdata <= (others => '0');
          sim_data <= sim_data;
        end if;
      end if;
    end if;
  end process;

-- DUT instance and connections
  skidbuffer_inst : axis_flow_control
  generic map (
    C_S_AXIS_TDATA_WIDTH  => DATA_WIDTH
  )
  port map (
    AXIS_ACLK     => clk,
    AXIS_ARESETN  => rst_n,

    S_AXIS_TVALID => s_axis_tvalid,
    S_AXIS_TDATA  => s_axis_tdata, 
    S_AXIS_TSTRB  => s_axis_tstrb, 
    S_AXIS_TLAST  => s_axis_tlast, 
    S_AXIS_TREADY => s_axis_tready, 

    M_AXIS_TVALID => m_axis_tvalid, 
    M_AXIS_TDATA  => m_axis_tdata, 
    M_AXIS_TSTRB  => m_axis_tstrb, 
    M_AXIS_TLAST  => m_axis_tlast, 
    M_AXIS_TREADY => m_axis_tready,

    xon  => fifo_empty, 
    xoff => fifo_full
  );

end bh;

ghdl/axis-flow-control/wave.vcd
$date
  Wed Jun 21 10:41:17 2023
$end
$version
  GHDL v0
$end
$timescale
  1 fs
$end
$scope module standard $end
$upscope $end
$scope module std_logic_1164 $end
$upscope $end
$scope module numeric_std $end
$upscope $end
$scope module tb_axis $end
$var reg 1 ! sim_valid_data $end
$var reg 1 " sim_ready_data $end
$var reg 8 # sim_data[7:0] $end
$var reg 1 $ s_axis_tvalid $end
$var reg 8 % s_axis_tdata[7:0] $end
$var reg 1 & s_axis_tstrb[0:0] $end
$var reg 1 ' s_axis_tlast $end
$var reg 1 ( s_axis_tready $end
$var reg 1 ) m_axis_tvalid $end
$var reg 8 * m_axis_tdata[7:0] $end
$var reg 1 + m_axis_tstrb[0:0] $end
$var reg 1 , m_axis_tlast $end
$var reg 1 - m_axis_tready $end
$var reg 1 . fifo_full $end
$var reg 1 / fifo_empty $end
$var reg 1 0 clk $end
$var reg 1 1 rst_n $end
$var reg 8 2 clk_count[7:0] $end
$scope module skidbuffer_inst $end
$var reg 1 3 axis_aclk $end
$var reg 1 4 axis_aresetn $end
$var reg 1 5 s_axis_tvalid $end
$var reg 8 6 s_axis_tdata[7:0] $end
$var reg 1 7 s_axis_tstrb[0:0] $end
$var reg 1 8 s_axis_tlast $end
$var reg 1 9 s_axis_tready $end
$var reg 1 : m_axis_tvalid $end
$var reg 8 ; m_axis_tdata[7:0] $end
$var reg 1 < m_axis_tstrb[0:0] $end
$var reg 1 = m_axis_tlast $end
$var reg 1 > m_axis_tready $end
$var reg 1 ? xon $end
$var reg 1 @ xoff $end
$var reg 1 A aclk $end
$var reg 1 B aresetn $end
$var reg 1 C i_s_axis_tvalid $end
$var reg 8 D i_s_axis_tdata[7:0] $end
$var reg 9 E i_axis_data_strb[8:0] $end
$var reg 1 F i_s_axis_tstrb[0:0] $end
$var reg 1 G i_s_axis_tlast $end
$var reg 1 H o_s_axis_tready $end
$var reg 1 I o_m_axis_tvalid $end
$var reg 8 J o_m_axis_tdata[7:0] $end
$var reg 9 K o_axis_data_strb[8:0] $end
$var reg 1 L o_m_axis_tstrb[0:0] $end
$var reg 1 M o_m_axis_tlast $end
$var reg 1 N i_m_axis_tready $end
$var reg 1 O en_tready $end
$var reg 1 P tready_buf $end
$scope module skidbuffer_inst $end
$var reg 1 Q clock $end
$var reg 1 R reset_n $end
$var reg 1 S s_valid_i $end
$var reg 1 T s_last_i $end
$var reg 1 U s_ready_o $end
$var reg 9 V s_data_i[8:0] $end
$var reg 1 W m_valid_o $end
$var reg 1 X m_last_o $end
$var reg 1 Y m_ready_i $end
$var reg 9 Z m_data_o[8:0] $end
$var reg 9 [ reg_data[8:0] $end
$var reg 1 \ reg_last $end
$var reg 1 ] reg_valid $end
$var reg 1 ^ reg_ready $end
$var reg 9 _ skd_data[8:0] $end
$var reg 1 ` skd_last $end
$var reg 9 a out_data[8:0] $end
$var reg 1 b out_last $end
$scope module gen_data_register $end
$upscope $end
$upscope $end
$upscope $end
$upscope $end
$enddefinitions $end
#0
0!
1"
bUUUUUUUU #
0$
bUUUUUUUU %
bU &
U'
U(
U)
bUUUUUUUU *
bU +
U,
0-
U.
U/
10
01
b00000000 2
13
04
05
bUUUUUUUU 6
bU 7
U8
U9
U:
bUUUUUUUU ;
bU <
U=
0>
U?
U@
1A
0B
0C
bUUUUUUUU D
bUUUUUUUUU E
bU F
UG
UH
UI
bUUUUUUUU J
bUUUUUUUUU K
bU L
UM
0N
UO
0P
1Q
0R
0S
UT
UU
bUUUUUUUUU V
UW
UX
0Y
bUUUUUUUUU Z
bUUUUUUUUU [
U\
U]
U^
bUUUUUUUUU _
U`
bUUUUUUUUU a
Ub
#2500000
00
03
0A
0Q
#5000000
b00000000 #
b00000000 %
b0 &
0'
0(
0)
b00000000 *
b0 +
0,
1-
0.
1/
10
b00000001 2
13
b00000000 6
b0 7
08
09
0:
b00000000 ;
b0 <
0=
1>
1?
0@
1A
b00000000 D
b000000000 E
b0 F
0G
0H
0I
b00000000 J
b000000000 K
b0 L
0M
1N
0O
1Q
0T
0U
b000000000 V
0W
0X
b000000000 Z
b000000000 [
0\
0]
0^
b000000000 _
0`
b000000000 a
0b
#6250000
11
14
1B
1R
#7500000
00
03
0A
0Q
#10000000
1!
10
b00000010 2
13
1A
1O
1P
1Q
1Y
#12500000
00
03
0A
0Q
#15000000
1$
b1 &
1(
10
b00000011 2
13
15
b1 7
19
1A
1C
b000000001 E
b1 F
1H
1Q
1S
1U
b000000001 V
1^
#17500000
00
03
0A
0Q
#20000000
b00000001 #
b00000001 %
1)
b1 +
10
b00000100 2
13
b00000001 6
1:
b1 <
1A
b00000001 D
b000000011 E
1I
b000000001 K
b1 L
1Q
b000000011 V
1W
b000000001 Z
b000000001 [
1]
b000000001 _
b000000001 a
#22500000
00
03
0A
0Q
#25000000
b00000010 #
b00000010 %
b00000001 *
10
b00000101 2
13
b00000010 6
b00000001 ;
1A
b00000010 D
b000000101 E
b00000001 J
b000000011 K
1Q
b000000101 V
b000000011 Z
b000000011 [
b000000011 _
b000000011 a
#27500000
00
03
0A
0Q
#30000000
b00000011 #
b00000011 %
b00000010 *
10
b00000110 2
13
b00000011 6
b00000010 ;
1A
b00000011 D
b000000111 E
b00000010 J
b000000101 K
1Q
b000000111 V
b000000101 Z
b000000101 [
b000000101 _
b000000101 a
#32500000
00
03
0A
0Q
#35000000
0"
b00000100 #
b00000100 %
1'
b00000011 *
10
b00000111 2
13
b00000100 6
18
b00000011 ;
1A
b00000100 D
b000001001 E
1G
b00000011 J
b000000111 K
1Q
1T
b000001001 V
b000000111 Z
b000000111 [
b000000111 _
b000000111 a
#37500000
00
03
0A
0Q
#40000000
1"
b00000001 #
b00000001 %
0'
b00000100 *
1,
0-
10
b00001000 2
13
b00000001 6
08
b00000100 ;
1=
0>
1A
b00000001 D
b000000011 E
0G
b00000100 J
b000001001 K
1M
0N
0P
1Q
0T
b000000011 V
1X
0Y
b000001001 Z
b000001001 [
1\
b000001001 _
1`
b000001001 a
1b
#42500000
00
03
0A
0Q
#45000000
b00000010 #
b00000010 %
0(
1-
10
b00001001 2
13
b00000010 6
09
1>
1A
b00000010 D
b000000101 E
0H
1N
1P
1Q
0U
b000000101 V
1Y
0^
b000000011 _
0`
#47500000
00
03
0A
0Q
#50000000
1(
b00000001 *
0,
10
b00001010 2
13
19
b00000001 ;
0=
1A
1H
b00000001 J
b000000011 K
0M
1Q
1U
0X
b000000011 Z
b000000011 [
0\
1^
b000000011 a
0b
#52500000
00
03
0A
0Q
#55000000
0"
b00000011 #
b00000011 %
b00000010 *
10
b00001011 2
13
b00000011 6
b00000010 ;
1A
b00000011 D
b000000111 E
b00000010 J
b000000101 K
1Q
b000000111 V
b000000101 Z
b000000101 [
b000000101 _
b000000101 a
#57500000
00
03
0A
0Q
#60000000
b00000100 #
b00000100 %
1'
b00000011 *
0-
10
b00001100 2
13
b00000100 6
18
b00000011 ;
0>
1A
b00000100 D
b000001001 E
1G
b00000011 J
b000000111 K
0N
0P
1Q
1T
b000001001 V
0Y
b000000111 Z
b000000111 [
b000000111 _
b000000111 a
#62500000
00
03
0A
0Q
#65000000
1"
b00000001 #
b00000001 %
0'
0(
10
b00001101 2
13
b00000001 6
08
09
1A
b00000001 D
b000000011 E
0G
0H
1Q
0T
0U
b000000011 V
0^
b000001001 _
1`
#67500000
00
03
0A
0Q
#70000000
0"
1-
10
b00001110 2
13
1>
1A
1N
1P
1Q
1Y
#72500000
00
03
0A
0Q
#75000000
1"
1(
b00000100 *
1,
0-
10
b00001111 2
13
19
b00000100 ;
1=
0>
1A
1H
b00000100 J
b000001001 K
1M
0N
0P
1Q
1U
1X
0Y
b000001001 Z
b000001001 [
1\
1^
b000001001 a
1b
#77500000
00
03
0A
0Q
#80000000
b00000010 #
b00000010 %
0(
1-
10
b00010000 2
13
b00000010 6
09
1>
1A
b00000010 D
b000000101 E
0H
1N
1P
1Q
0U
b000000101 V
1Y
0^
b000000011 _
0`
#82500000
00
03
0A
0Q
#85000000
1(
b00000001 *
0,
10
b00010001 2
13
19
b00000001 ;
0=
1A
1H
b00000001 J
b000000011 K
0M
1Q
1U
0X
b000000011 Z
b000000011 [
0\
1^
b000000011 a
0b
#87500000
00
03
0A
0Q
#90000000
0!
b00000011 #
b00000011 %
b00000010 *
10
b00010010 2
13
b00000011 6
b00000010 ;
1A
b00000011 D
b000000111 E
b00000010 J
b000000101 K
1Q
b000000111 V
b000000101 Z
b000000101 [
b000000101 _
b000000101 a
#92500000
00
03
0A
0Q
#95000000
0$
b00000000 %
b0 &
b00000011 *
10
b00010011 2
13
05
b00000000 6
b0 7
b00000011 ;
1A
0C
b00000000 D
b000000000 E
b0 F
b00000011 J
b000000111 K
1Q
0S
b000000000 V
b000000111 Z
b000000111 [
b000000111 _
b000000111 a
#97500000
00
03
0A
0Q
#100000000
0)
b00000000 *
b0 +
10
b00010100 2
13
0:
b00000000 ;
b0 <
1A
0I
b00000000 J
b000000000 K
b0 L
1Q
0W
b000000000 Z
b000000000 [
0]
b000000000 _
b000000000 a
#102500000
00
03
0A
0Q
#105000000
1!
10
b00010101 2
13
1A
1Q
#107500000
00
03
0A
0Q
#110000000
b00000100 #
1$
b00000100 %
b1 &
10
b00010110 2
13
15
b00000100 6
b1 7
1A
1C
b00000100 D
b000001001 E
b1 F
1Q
1S
b000001001 V
#112500000
00
03
0A
0Q
#115000000
0!
b00000001 #
b00000001 %
1)
b00000100 *
b1 +
10
b00010111 2
13
b00000001 6
1:
b00000100 ;
b1 <
1A
b00000001 D
b000000011 E
1I
b00000100 J
b000001001 K
b1 L
1Q
b000000011 V
1W
b000001001 Z
b000001001 [
1]
b000001001 _
b000001001 a
#117500000
00
03
0A
0Q
#120000000
1!
0$
b00000000 %
b0 &
b00000001 *
10
b00011000 2
13
05
b00000000 6
b0 7
b00000001 ;
1A
0C
b00000000 D
b000000000 E
b0 F
b00000001 J
b000000011 K
1Q
0S
b000000000 V
b000000011 Z
b000000011 [
b000000011 _
b000000011 a
#122500000
00
03
0A
0Q
#125000000
b00000010 #
1$
b00000010 %
b1 &
0)
b00000000 *
b0 +
10
b00011001 2
13
15
b00000010 6
b1 7
0:
b00000000 ;
b0 <
1A
1C
b00000010 D
b000000101 E
b1 F
0I
b00000000 J
b000000000 K
b0 L
1Q
1S
b000000101 V
0W
b000000000 Z
b000000000 [
0]
b000000000 _
b000000000 a
#127500000
00
03
0A
0Q
#130000000
0!
b00000011 #
b00000011 %
1)
b00000010 *
b1 +
10
b00011010 2
13
b00000011 6
1:
b00000010 ;
b1 <
1A
b00000011 D
b000000111 E
1I
b00000010 J
b000000101 K
b1 L
1Q
b000000111 V
1W
b000000101 Z
b000000101 [
1]
b000000101 _
b000000101 a
#132500000
00
03
0A
0Q
#135000000
0$
b00000000 %
b0 &
b00000011 *
10
b00011011 2
13
05
b00000000 6
b0 7
b00000011 ;
1A
0C
b00000000 D
b000000000 E
b0 F
b00000011 J
b000000111 K
1Q
0S
b000000000 V
b000000111 Z
b000000111 [
b000000111 _
b000000111 a
#137500000
00
03
0A
0Q
#140000000
0)
b00000000 *
b0 +
10
b00011100 2
13
0:
b00000000 ;
b0 <
1A
0I
b00000000 J
b000000000 K
b0 L
1Q
0W
b000000000 Z
b000000000 [
0]
b000000000 _
b000000000 a
#142500000
00
03
0A
0Q
#145000000
10
b00011101 2
13
1A
1Q
#147500000
00
03
0A
0Q
#150000000
10
b00011110 2
13
1A
1Q
#152500000
00
03
0A
0Q
#155000000
10
b00011111 2
13
1A
1Q
#157500000
00
03
0A
0Q
#160000000
1!
10
b00100000 2
13
1A
1Q
#162500000
00
03
0A
0Q
#165000000
b00000100 #
1$
b00000100 %
b1 &
10
b00100001 2
13
15
b00000100 6
b1 7
1A
1C
b00000100 D
b000001001 E
b1 F
1Q
1S
b000001001 V
#167500000
00
03
0A
0Q
